{"action":{"identity":{"address":"N\u0000sourcecred\u0000core\u0000IDENTITY\u0000qSqDm0yiViDHwDWhP6o7HA\u0000","aliases":[],"id":"qSqDm0yiViDHwDWhP6o7HA","name":"Ekkeharta","subtype":"USER"},"type":"CREATE_IDENTITY"},"ledgerTimestamp":1642096891703,"uuid":"uJD1lo61GEZoV8FwydqWfQ","version":"1"}
{"action":{"alias":{"address":"N\u0000sourcecred\u0000discord\u0000MEMBER\u0000user\u0000131942579985055744\u0000","description":"discord/Ekkeharta#3447"},"identityId":"qSqDm0yiViDHwDWhP6o7HA","type":"ADD_ALIAS"},"ledgerTimestamp":1642096891703,"uuid":"FBeCkTV7qQyopYXrcJVobQ","version":"1"}
{"action":{"identity":{"address":"N\u0000sourcecred\u0000core\u0000IDENTITY\u0000euW99YR9WlKvJi6Q1DVxQQ\u0000","aliases":[],"id":"euW99YR9WlKvJi6Q1DVxQQ","name":"Leyoric","subtype":"USER"},"type":"CREATE_IDENTITY"},"ledgerTimestamp":1642096891704,"uuid":"bZpR2OIMNArAkWBWqiGdqQ","version":"1"}
{"action":{"alias":{"address":"N\u0000sourcecred\u0000discord\u0000MEMBER\u0000user\u0000134423116959973378\u0000","description":"discord/Leyoric#9095"},"identityId":"euW99YR9WlKvJi6Q1DVxQQ","type":"ADD_ALIAS"},"ledgerTimestamp":1642096891704,"uuid":"ymZ1OOnS8pdjbAx4m9F82A","version":"1"}
{"action":{"identity":{"address":"N\u0000sourcecred\u0000core\u0000IDENTITY\u0000oNlPIDpeEMlkwL8UYtBr1g\u0000","aliases":[],"id":"oNlPIDpeEMlkwL8UYtBr1g","name":"HomicidalChicken","subtype":"USER"},"type":"CREATE_IDENTITY"},"ledgerTimestamp":1642096891704,"uuid":"QEyE09S8YoPmXd7GPvRwOg","version":"1"}
{"action":{"alias":{"address":"N\u0000sourcecred\u0000discord\u0000MEMBER\u0000user\u0000221288305222877185\u0000","description":"discord/HomicidalChicken#8326"},"identityId":"oNlPIDpeEMlkwL8UYtBr1g","type":"ADD_ALIAS"},"ledgerTimestamp":1642096891705,"uuid":"HJzj6kekvkIm5b0VQsveMQ","version":"1"}
{"action":{"identity":{"address":"N\u0000sourcecred\u0000core\u0000IDENTITY\u0000qcXYSMhDbKsRbWOq9E1lNA\u0000","aliases":[],"id":"qcXYSMhDbKsRbWOq9E1lNA","name":"Dank-Mona","subtype":"USER"},"type":"CREATE_IDENTITY"},"ledgerTimestamp":1642096891705,"uuid":"WurNk0FdbjLR8Nf8eI1j5g","version":"1"}
{"action":{"alias":{"address":"N\u0000sourcecred\u0000discord\u0000MEMBER\u0000user\u0000225311920754786304\u0000","description":"discord/Dank-Mona#4426"},"identityId":"qcXYSMhDbKsRbWOq9E1lNA","type":"ADD_ALIAS"},"ledgerTimestamp":1642096891705,"uuid":"x9MyTqCGei6jll0XztDDIA","version":"1"}
{"action":{"identity":{"address":"N\u0000sourcecred\u0000core\u0000IDENTITY\u0000AJIk0MDdXDflP7e7Jz11Eg\u0000","aliases":[],"id":"AJIk0MDdXDflP7e7Jz11Eg","name":"ufkhan97","subtype":"USER"},"type":"CREATE_IDENTITY"},"ledgerTimestamp":1642096891705,"uuid":"r1QcQo6ikdvuOxc6DdFwDg","version":"1"}
{"action":{"alias":{"address":"N\u0000sourcecred\u0000discord\u0000MEMBER\u0000user\u0000259178972301099008\u0000","description":"discord/ufkhan97#4345"},"identityId":"AJIk0MDdXDflP7e7Jz11Eg","type":"ADD_ALIAS"},"ledgerTimestamp":1642096891706,"uuid":"Nzj1Nh6CrWxrkcyHKE1Afw","version":"1"}
{"action":{"identity":{"address":"N\u0000sourcecred\u0000core\u0000IDENTITY\u0000abbugaXtn28tEHNXqL7LMg\u0000","aliases":[],"id":"abbugaXtn28tEHNXqL7LMg","name":"-BrianMillsJr","subtype":"USER"},"type":"CREATE_IDENTITY"},"ledgerTimestamp":1642096891706,"uuid":"R7OtXSaYVoC4BKrLqd405w","version":"1"}
{"action":{"alias":{"address":"N\u0000sourcecred\u0000discord\u0000MEMBER\u0000user\u0000325811370195156994\u0000","description":"discord/-BrianMillsJr#5987"},"identityId":"abbugaXtn28tEHNXqL7LMg","type":"ADD_ALIAS"},"ledgerTimestamp":1642096891706,"uuid":"2R3nrwEgdXw8yxJ8pvDNFg","version":"1"}
{"action":{"identity":{"address":"N\u0000sourcecred\u0000core\u0000IDENTITY\u0000emc7HZr0xE74N4L7ZEYLDQ\u0000","aliases":[],"id":"emc7HZr0xE74N4L7ZEYLDQ","name":"crossoveranx","subtype":"USER"},"type":"CREATE_IDENTITY"},"ledgerTimestamp":1642096891706,"uuid":"4BcnAZBapJoyq3sM79nyJA","version":"1"}
{"action":{"alias":{"address":"N\u0000sourcecred\u0000discord\u0000MEMBER\u0000user\u0000379030669201768448\u0000","description":"discord/crossoveranx#1832"},"identityId":"emc7HZr0xE74N4L7ZEYLDQ","type":"ADD_ALIAS"},"ledgerTimestamp":1642096891706,"uuid":"MiLhXmIbrX3fERBsdaWLEw","version":"1"}
{"action":{"identity":{"address":"N\u0000sourcecred\u0000core\u0000IDENTITY\u0000b3RQ7kRgN57eWx70SpO4YA\u0000","aliases":[],"id":"b3RQ7kRgN57eWx70SpO4YA","name":"Keturin","subtype":"USER"},"type":"CREATE_IDENTITY"},"ledgerTimestamp":1642096891706,"uuid":"ok9k966R6BMvbz93RyLDDw","version":"1"}
{"action":{"alias":{"address":"N\u0000sourcecred\u0000discord\u0000MEMBER\u0000user\u0000455016695174529025\u0000","description":"discord/Keturin#6669"},"identityId":"b3RQ7kRgN57eWx70SpO4YA","type":"ADD_ALIAS"},"ledgerTimestamp":1642096891706,"uuid":"OmzYNhz0aM0rYoq0ptXDpQ","version":"1"}
{"action":{"identity":{"address":"N\u0000sourcecred\u0000core\u0000IDENTITY\u0000ZLOW51V8UnpfQDJFKByzlg\u0000","aliases":[],"id":"ZLOW51V8UnpfQDJFKByzlg","name":"llllvvuu","subtype":"USER"},"type":"CREATE_IDENTITY"},"ledgerTimestamp":1642096891707,"uuid":"Bv7qI2gX5qBTexhGl7w3JA","version":"1"}
{"action":{"alias":{"address":"N\u0000sourcecred\u0000discord\u0000MEMBER\u0000user\u0000522402421566078978\u0000","description":"discord/llllvvuu#1782"},"identityId":"ZLOW51V8UnpfQDJFKByzlg","type":"ADD_ALIAS"},"ledgerTimestamp":1642096891707,"uuid":"Wh5FKKuZY14zVZwopdYr6g","version":"1"}
{"action":{"identity":{"address":"N\u0000sourcecred\u0000core\u0000IDENTITY\u0000nmAHnsxJ4nXbWlf9g8U41A\u0000","aliases":[],"id":"nmAHnsxJ4nXbWlf9g8U41A","name":"Mike-Elias","subtype":"USER"},"type":"CREATE_IDENTITY"},"ledgerTimestamp":1642096891707,"uuid":"BvasLlKdLXMGy7wgM7zH9A","version":"1"}
{"action":{"alias":{"address":"N\u0000sourcecred\u0000discord\u0000MEMBER\u0000user\u0000626178021120016395\u0000","description":"discord/Mike-Elias#4724"},"identityId":"nmAHnsxJ4nXbWlf9g8U41A","type":"ADD_ALIAS"},"ledgerTimestamp":1642096891707,"uuid":"Mm1vxlmoeokCdwgbQwb37w","version":"1"}
{"action":{"identity":{"address":"N\u0000sourcecred\u0000core\u0000IDENTITY\u000039N9YIQ3WwDTGmk2w2uLBg\u0000","aliases":[],"id":"39N9YIQ3WwDTGmk2w2uLBg","name":"Shamburgularara---XXI","subtype":"USER"},"type":"CREATE_IDENTITY"},"ledgerTimestamp":1642096891707,"uuid":"BPO41AdIjulIRFNVlQnMow","version":"1"}
{"action":{"alias":{"address":"N\u0000sourcecred\u0000discord\u0000MEMBER\u0000user\u0000718139779509911623\u0000","description":"discord/Shamburgularara---XXI#7217"},"identityId":"39N9YIQ3WwDTGmk2w2uLBg","type":"ADD_ALIAS"},"ledgerTimestamp":1642096891707,"uuid":"9DP885uQegZ23maBj4idwA","version":"1"}
{"action":{"identity":{"address":"N\u0000sourcecred\u0000core\u0000IDENTITY\u0000zH9ndQ4KkmMQmCAYDYUjwQ\u0000","aliases":[],"id":"zH9ndQ4KkmMQmCAYDYUjwQ","name":"darren","subtype":"USER"},"type":"CREATE_IDENTITY"},"ledgerTimestamp":1642096891707,"uuid":"899Sx46Swn4tL5ulrzaqzA","version":"1"}
{"action":{"alias":{"address":"N\u0000sourcecred\u0000discord\u0000MEMBER\u0000user\u0000852800209611653120\u0000","description":"discord/darren#1994"},"identityId":"zH9ndQ4KkmMQmCAYDYUjwQ","type":"ADD_ALIAS"},"ledgerTimestamp":1642096891707,"uuid":"Eph3h6HNwlK8wQntXBqh0Q","version":"1"}
{"action":{"identity":{"address":"N\u0000sourcecred\u0000core\u0000IDENTITY\u00004xAvDI2FlIDrq5yNYyggQw\u0000","aliases":[],"id":"4xAvDI2FlIDrq5yNYyggQw","name":"tone123456789","subtype":"USER"},"type":"CREATE_IDENTITY"},"ledgerTimestamp":1642096891708,"uuid":"KLm6QupP7AtRPVrImxUK7w","version":"1"}
{"action":{"alias":{"address":"N\u0000sourcecred\u0000discord\u0000MEMBER\u0000user\u0000902331794387533864\u0000","description":"discord/tone123456789#6303"},"identityId":"4xAvDI2FlIDrq5yNYyggQw","type":"ADD_ALIAS"},"ledgerTimestamp":1642096891708,"uuid":"d8VeFXAsZcLjH0zb6uyU3g","version":"1"}
{"action":{"identity":{"address":"N\u0000sourcecred\u0000core\u0000IDENTITY\u0000Pe6A0Kl0e6xwjb29MQ7rig\u0000","aliases":[],"id":"Pe6A0Kl0e6xwjb29MQ7rig","name":"sam76021","subtype":"USER"},"type":"CREATE_IDENTITY"},"ledgerTimestamp":1642096891708,"uuid":"bsE1W3qAdXWLIzi6jHggWw","version":"1"}
{"action":{"alias":{"address":"N\u0000sourcecred\u0000discord\u0000MEMBER\u0000user\u0000905595868768501831\u0000","description":"discord/sam76021#2389"},"identityId":"Pe6A0Kl0e6xwjb29MQ7rig","type":"ADD_ALIAS"},"ledgerTimestamp":1642096891708,"uuid":"FjqaLu4yKIev988ecaCO2w","version":"1"}
{"action":{"identity":{"address":"N\u0000sourcecred\u0000core\u0000IDENTITY\u0000W3w8X7cGwvt7fp5XrVskag\u0000","aliases":[],"id":"W3w8X7cGwvt7fp5XrVskag","name":"versusmikehistory","subtype":"USER"},"type":"CREATE_IDENTITY"},"ledgerTimestamp":1642096891708,"uuid":"DIQDRO7gQIK8U1xWJ7HPrA","version":"1"}
{"action":{"alias":{"address":"N\u0000sourcecred\u0000discord\u0000MEMBER\u0000user\u0000921920605400469554\u0000","description":"discord/versusmikehistory#0363"},"identityId":"W3w8X7cGwvt7fp5XrVskag","type":"ADD_ALIAS"},"ledgerTimestamp":1642096891708,"uuid":"DRtDai1GF3H8r4hlEbOUQw","version":"1"}
{"action":{"identity":{"address":"N\u0000sourcecred\u0000core\u0000IDENTITY\u0000qkGQO5ba65R7h0J1SxK2fA\u0000","aliases":[],"id":"qkGQO5ba65R7h0J1SxK2fA","name":"SourceCred-Braid-Bot","subtype":"BOT"},"type":"CREATE_IDENTITY"},"ledgerTimestamp":1642096891708,"uuid":"WBjxPZLl23rJmBAJQKMwHA","version":"1"}
{"action":{"alias":{"address":"N\u0000sourcecred\u0000discord\u0000MEMBER\u0000bot\u0000930561335492767744\u0000","description":"discord/SourceCred-Braid-Bot#3393"},"identityId":"qkGQO5ba65R7h0J1SxK2fA","type":"ADD_ALIAS"},"ledgerTimestamp":1642096891708,"uuid":"YoNbUrCEGzK1UVS8Zg7Zsg","version":"1"}
{"action":{"identity":{"address":"N\u0000sourcecred\u0000core\u0000IDENTITY\u0000rp9eJcE639XgmVT1V6sj7g\u0000","aliases":[],"id":"rp9eJcE639XgmVT1V6sj7g","name":"decentralion","subtype":"USER"},"type":"CREATE_IDENTITY"},"ledgerTimestamp":1642096892188,"uuid":"soGUO3M78XZ8z56A77HGIw","version":"1"}
{"action":{"alias":{"address":"N\u0000sourcecred\u0000github\u0000USERLIKE\u0000USER\u0000decentralion\u0000","description":"github/[@decentralion](https://github.com/decentralion)"},"identityId":"rp9eJcE639XgmVT1V6sj7g","type":"ADD_ALIAS"},"ledgerTimestamp":1642096892188,"uuid":"OkaBJYG6ioRi4idyZfL9OA","version":"1"}
{"action":{"identity":{"address":"N\u0000sourcecred\u0000core\u0000IDENTITY\u0000ZIGr9w3s1sxLCpSphMqqlg\u0000","aliases":[],"id":"ZIGr9w3s1sxLCpSphMqqlg","name":"credbot","subtype":"BOT"},"type":"CREATE_IDENTITY"},"ledgerTimestamp":1642096892188,"uuid":"zbupbPndX205W194t1KA2Q","version":"1"}
{"action":{"alias":{"address":"N\u0000sourcecred\u0000github\u0000USERLIKE\u0000BOT\u0000credbot\u0000","description":"github/[@credbot](https://github.com/credbot)"},"identityId":"ZIGr9w3s1sxLCpSphMqqlg","type":"ADD_ALIAS"},"ledgerTimestamp":1642096892188,"uuid":"RXQu0WwO5PIj9Ij2SlBTYg","version":"1"}
{"action":{"identity":{"address":"N\u0000sourcecred\u0000core\u0000IDENTITY\u0000Vt2674qUGfxL5ZezDTVrzA\u0000","aliases":[],"id":"Vt2674qUGfxL5ZezDTVrzA","name":"wchargin","subtype":"USER"},"type":"CREATE_IDENTITY"},"ledgerTimestamp":1642096892189,"uuid":"Cx6ieppR8o8WWJeXcvpKyg","version":"1"}
{"action":{"alias":{"address":"N\u0000sourcecred\u0000github\u0000USERLIKE\u0000USER\u0000wchargin\u0000","description":"github/[@wchargin](https://github.com/wchargin)"},"identityId":"Vt2674qUGfxL5ZezDTVrzA","type":"ADD_ALIAS"},"ledgerTimestamp":1642096892189,"uuid":"9DXbBeEMJ4DHmWYSKdJaAQ","version":"1"}
{"action":{"identity":{"address":"N\u0000sourcecred\u0000core\u0000IDENTITY\u0000ta1ouAqKPYSnb0BK3aoFxA\u0000","aliases":[],"id":"ta1ouAqKPYSnb0BK3aoFxA","name":"SourceCred","subtype":"PROJECT"},"type":"CREATE_IDENTITY"},"ledgerTimestamp":1642096892261,"uuid":"RRl4wmMEP0pj42aVuaVNKA","version":"1"}
{"action":{"identityId":"ta1ouAqKPYSnb0BK3aoFxA","type":"TOGGLE_ACTIVATION"},"ledgerTimestamp":1642096892261,"uuid":"g67m66hMCpA90jqlWx7YHA","version":"1"}
{"action":{"identity":{"address":"N\u0000sourcecred\u0000core\u0000IDENTITY\u0000oYNtpv48ZTriGAhlJO6h8g\u0000","aliases":[],"id":"oYNtpv48ZTriGAhlJO6h8g","name":"yung-calibri","subtype":"USER"},"type":"CREATE_IDENTITY"},"ledgerTimestamp":1645405359993,"uuid":"Qcga32NQnNo4y7oEOw5MaQ","version":"1"}
{"action":{"alias":{"address":"N\u0000sourcecred\u0000discord\u0000MEMBER\u0000user\u0000132055527504084992\u0000","description":"discord/yung-calibri#0225"},"identityId":"oYNtpv48ZTriGAhlJO6h8g","type":"ADD_ALIAS"},"ledgerTimestamp":1645405359993,"uuid":"tv6LikeIzao1jYRsz3XRGQ","version":"1"}
{"action":{"identity":{"address":"N\u0000sourcecred\u0000core\u0000IDENTITY\u0000PtWk70QK6dlCq5DGN4vXjQ\u0000","aliases":[],"id":"PtWk70QK6dlCq5DGN4vXjQ","name":"LaRiccia","subtype":"USER"},"type":"CREATE_IDENTITY"},"ledgerTimestamp":1645405359994,"uuid":"xDXtxIl3Zyk2F1h2m0VLmA","version":"1"}
{"action":{"alias":{"address":"N\u0000sourcecred\u0000discord\u0000MEMBER\u0000user\u0000193041322150461440\u0000","description":"discord/LaRiccia#6314"},"identityId":"PtWk70QK6dlCq5DGN4vXjQ","type":"ADD_ALIAS"},"ledgerTimestamp":1645405359994,"uuid":"eJpElzFD0IlTZ8V2J5Ivbg","version":"1"}
{"action":{"identity":{"address":"N\u0000sourcecred\u0000core\u0000IDENTITY\u0000K8QGcnNJRQWnli6Nm1ZZbw\u0000","aliases":[],"id":"K8QGcnNJRQWnli6Nm1ZZbw","name":"rabage","subtype":"USER"},"type":"CREATE_IDENTITY"},"ledgerTimestamp":1645405359994,"uuid":"OmXnr7XOptbm3FVWvuNYJw","version":"1"}
{"action":{"alias":{"address":"N\u0000sourcecred\u0000discord\u0000MEMBER\u0000user\u0000220712729172770816\u0000","description":"discord/rabage#0897"},"identityId":"K8QGcnNJRQWnli6Nm1ZZbw","type":"ADD_ALIAS"},"ledgerTimestamp":1645405359995,"uuid":"vGIeyu6kwEYEslYBL3mOGw","version":"1"}
{"action":{"identity":{"address":"N\u0000sourcecred\u0000core\u0000IDENTITY\u0000KTzEQ1wLrs3mbru5djIyPw\u0000","aliases":[],"id":"KTzEQ1wLrs3mbru5djIyPw","name":"chicken-sharoofi","subtype":"USER"},"type":"CREATE_IDENTITY"},"ledgerTimestamp":1645405359995,"uuid":"hq6JiAv7lfVKdobJoaP4jQ","version":"1"}
{"action":{"alias":{"address":"N\u0000sourcecred\u0000discord\u0000MEMBER\u0000user\u0000341767134495375363\u0000","description":"discord/chicken-sharoofi#4385"},"identityId":"KTzEQ1wLrs3mbru5djIyPw","type":"ADD_ALIAS"},"ledgerTimestamp":1645405359995,"uuid":"OcmRZOriJg6FaRNGb7RNGQ","version":"1"}
{"action":{"identity":{"address":"N\u0000sourcecred\u0000core\u0000IDENTITY\u000099Y0ON5I2ZBObqy3W0fd5Q\u0000","aliases":[],"id":"99Y0ON5I2ZBObqy3W0fd5Q","name":"MantisClone","subtype":"USER"},"type":"CREATE_IDENTITY"},"ledgerTimestamp":1645405359995,"uuid":"w63FXsXWweZqbjy4SRJXTg","version":"1"}
{"action":{"alias":{"address":"N\u0000sourcecred\u0000discord\u0000MEMBER\u0000user\u0000369700858742571008\u0000","description":"discord/MantisClone#2619"},"identityId":"99Y0ON5I2ZBObqy3W0fd5Q","type":"ADD_ALIAS"},"ledgerTimestamp":1645405359996,"uuid":"6q37GwxOjkJMrHxB1LS0dA","version":"1"}
{"action":{"identity":{"address":"N\u0000sourcecred\u0000core\u0000IDENTITY\u0000kygkbuKOVbLVq9IdTot7Lg\u0000","aliases":[],"id":"kygkbuKOVbLVq9IdTot7Lg","name":"heintess","subtype":"USER"},"type":"CREATE_IDENTITY"},"ledgerTimestamp":1645405359996,"uuid":"xK6NEWfa489W7SYn0aE2Ig","version":"1"}
{"action":{"alias":{"address":"N\u0000sourcecred\u0000discord\u0000MEMBER\u0000user\u0000398278221319372801\u0000","description":"discord/heintess#7769"},"identityId":"kygkbuKOVbLVq9IdTot7Lg","type":"ADD_ALIAS"},"ledgerTimestamp":1645405359996,"uuid":"veubW0pwr1ZL3M4Cmuq7dw","version":"1"}
{"action":{"identity":{"address":"N\u0000sourcecred\u0000core\u0000IDENTITY\u0000Yxji71sZM1VkmTLueZzYQg\u0000","aliases":[],"id":"Yxji71sZM1VkmTLueZzYQg","name":"JB87","subtype":"USER"},"type":"CREATE_IDENTITY"},"ledgerTimestamp":1645405359997,"uuid":"WIjwVvx09ecgMeatMJGqOw","version":"1"}
{"action":{"alias":{"address":"N\u0000sourcecred\u0000discord\u0000MEMBER\u0000user\u0000400321205724512267\u0000","description":"discord/JB87#8474"},"identityId":"Yxji71sZM1VkmTLueZzYQg","type":"ADD_ALIAS"},"ledgerTimestamp":1645405359997,"uuid":"ySRpFoYB1Z82xd9EmP0MUA","version":"1"}
{"action":{"identity":{"address":"N\u0000sourcecred\u0000core\u0000IDENTITY\u0000iyBHbR6he9A4NwIx78NrdA\u0000","aliases":[],"id":"iyBHbR6he9A4NwIx78NrdA","name":"rush0","subtype":"USER"},"type":"CREATE_IDENTITY"},"ledgerTimestamp":1645405359997,"uuid":"fJqzR5zYuYSbk4dhpaub4A","version":"1"}
{"action":{"alias":{"address":"N\u0000sourcecred\u0000discord\u0000MEMBER\u0000user\u0000409745838441758721\u0000","description":"discord/rush0#5067"},"identityId":"iyBHbR6he9A4NwIx78NrdA","type":"ADD_ALIAS"},"ledgerTimestamp":1645405359997,"uuid":"8Iodubd8FaZ8MawWgYFo5w","version":"1"}
{"action":{"identity":{"address":"N\u0000sourcecred\u0000core\u0000IDENTITY\u0000Lz1wxE2WPwKMmrg16y8Nlg\u0000","aliases":[],"id":"Lz1wxE2WPwKMmrg16y8Nlg","name":"bestape","subtype":"USER"},"type":"CREATE_IDENTITY"},"ledgerTimestamp":1645405359998,"uuid":"BTOcxrz2JkZbVZOzhMoJaQ","version":"1"}
{"action":{"alias":{"address":"N\u0000sourcecred\u0000discord\u0000MEMBER\u0000user\u0000476451739516534799\u0000","description":"discord/bestape#3069"},"identityId":"Lz1wxE2WPwKMmrg16y8Nlg","type":"ADD_ALIAS"},"ledgerTimestamp":1645405359998,"uuid":"R11ptovdRZkVpKswSDu8jA","version":"1"}
{"action":{"identity":{"address":"N\u0000sourcecred\u0000core\u0000IDENTITY\u0000ZKnyOSPKjx7TAX76avTgrw\u0000","aliases":[],"id":"ZKnyOSPKjx7TAX76avTgrw","name":"GuavaGabriel","subtype":"USER"},"type":"CREATE_IDENTITY"},"ledgerTimestamp":1645405359998,"uuid":"QLVdfKO79Jr5YYDfkt3JSQ","version":"1"}
{"action":{"alias":{"address":"N\u0000sourcecred\u0000discord\u0000MEMBER\u0000user\u0000579305699281207307\u0000","description":"discord/GuavaGabriel#6530"},"identityId":"ZKnyOSPKjx7TAX76avTgrw","type":"ADD_ALIAS"},"ledgerTimestamp":1645405359998,"uuid":"bNSvVOjDRZHKgBKFZUWTLQ","version":"1"}
{"action":{"identity":{"address":"N\u0000sourcecred\u0000core\u0000IDENTITY\u0000bAOrWhXkQvIVBLZB3oglDg\u0000","aliases":[],"id":"bAOrWhXkQvIVBLZB3oglDg","name":"eugene---SCRF","subtype":"USER"},"type":"CREATE_IDENTITY"},"ledgerTimestamp":1645405359999,"uuid":"tRW2gb0ki66LHwxRD6b21w","version":"1"}
{"action":{"alias":{"address":"N\u0000sourcecred\u0000discord\u0000MEMBER\u0000user\u0000620452002425470977\u0000","description":"discord/eugene---SCRF#1706"},"identityId":"bAOrWhXkQvIVBLZB3oglDg","type":"ADD_ALIAS"},"ledgerTimestamp":1645405359999,"uuid":"NvtB60y966a3GwR9GFkS6w","version":"1"}
{"action":{"identity":{"address":"N\u0000sourcecred\u0000core\u0000IDENTITY\u00009DyaXLOprp14Ka1tRz266A\u0000","aliases":[],"id":"9DyaXLOprp14Ka1tRz266A","name":"hebbianloop","subtype":"USER"},"type":"CREATE_IDENTITY"},"ledgerTimestamp":1645405359999,"uuid":"bfEzqxSecB1QQnWWmFJhYw","version":"1"}
{"action":{"alias":{"address":"N\u0000sourcecred\u0000discord\u0000MEMBER\u0000user\u0000646837640980856862\u0000","description":"discord/hebbianloop#5169"},"identityId":"9DyaXLOprp14Ka1tRz266A","type":"ADD_ALIAS"},"ledgerTimestamp":1645405359999,"uuid":"cywW87h07ud1d6rOo30jdw","version":"1"}
{"action":{"identity":{"address":"N\u0000sourcecred\u0000core\u0000IDENTITY\u0000q7Ra78ecGFev2L77nBmlbA\u0000","aliases":[],"id":"q7Ra78ecGFev2L77nBmlbA","name":"Craig","subtype":"USER"},"type":"CREATE_IDENTITY"},"ledgerTimestamp":1645405359999,"uuid":"grkfqn6YiONcN0YvUYLOJQ","version":"1"}
{"action":{"alias":{"address":"N\u0000sourcecred\u0000discord\u0000MEMBER\u0000user\u0000655144629481635841\u0000","description":"discord/Craig#0979"},"identityId":"q7Ra78ecGFev2L77nBmlbA","type":"ADD_ALIAS"},"ledgerTimestamp":1645405360000,"uuid":"jsxBKFZ8W4vBlTAoAhabpA","version":"1"}
{"action":{"identity":{"address":"N\u0000sourcecred\u0000core\u0000IDENTITY\u0000HPYrBPiWoWvkOeAdc1CwCw\u0000","aliases":[],"id":"HPYrBPiWoWvkOeAdc1CwCw","name":"Xena","subtype":"USER"},"type":"CREATE_IDENTITY"},"ledgerTimestamp":1645405360000,"uuid":"53wZVwgdEV2s4v8EtexHPg","version":"1"}
{"action":{"alias":{"address":"N\u0000sourcecred\u0000discord\u0000MEMBER\u0000user\u0000690682149195481268\u0000","description":"discord/Xena#1289"},"identityId":"HPYrBPiWoWvkOeAdc1CwCw","type":"ADD_ALIAS"},"ledgerTimestamp":1645405360000,"uuid":"EEHZGAwHPpZB1YwILmirRA","version":"1"}
{"action":{"identity":{"address":"N\u0000sourcecred\u0000core\u0000IDENTITY\u00004BMdzB7xbRfNSnLjnkCWpw\u0000","aliases":[],"id":"4BMdzB7xbRfNSnLjnkCWpw","name":"dvwz","subtype":"USER"},"type":"CREATE_IDENTITY"},"ledgerTimestamp":1645405360000,"uuid":"Kw8ZJPmRDDJ9WAXR5kQ0IA","version":"1"}
{"action":{"alias":{"address":"N\u0000sourcecred\u0000discord\u0000MEMBER\u0000user\u0000707869170657919027\u0000","description":"discord/dvwz#7836"},"identityId":"4BMdzB7xbRfNSnLjnkCWpw","type":"ADD_ALIAS"},"ledgerTimestamp":1645405360000,"uuid":"Wmg2O0bTbgz1bWq3ofw8sg","version":"1"}
{"action":{"identity":{"address":"N\u0000sourcecred\u0000core\u0000IDENTITY\u0000oK69hl3j1TAa5B5BrI3N0Q\u0000","aliases":[],"id":"oK69hl3j1TAa5B5BrI3N0Q","name":"dnlmc","subtype":"USER"},"type":"CREATE_IDENTITY"},"ledgerTimestamp":1645405360000,"uuid":"06toRIMrJX8c6960XwI55w","version":"1"}
{"action":{"alias":{"address":"N\u0000sourcecred\u0000discord\u0000MEMBER\u0000user\u0000709960689682350150\u0000","description":"discord/dnlmc#6862"},"identityId":"oK69hl3j1TAa5B5BrI3N0Q","type":"ADD_ALIAS"},"ledgerTimestamp":1645405360000,"uuid":"tmokz9Vhz6snLnLVVHX4Ew","version":"1"}
{"action":{"identity":{"address":"N\u0000sourcecred\u0000core\u0000IDENTITY\u0000MMJZaNNQ5VoY6rqpt0QZXg\u0000","aliases":[],"id":"MMJZaNNQ5VoY6rqpt0QZXg","name":"Jessica-Sacher","subtype":"USER"},"type":"CREATE_IDENTITY"},"ledgerTimestamp":1645405360001,"uuid":"NYUmpNB1rXUd6Yv10Eivhg","version":"1"}
{"action":{"alias":{"address":"N\u0000sourcecred\u0000discord\u0000MEMBER\u0000user\u0000740984621482901546\u0000","description":"discord/Jessica-Sacher#8232"},"identityId":"MMJZaNNQ5VoY6rqpt0QZXg","type":"ADD_ALIAS"},"ledgerTimestamp":1645405360001,"uuid":"M9FmJdQWkSJK0mpsXkaI8A","version":"1"}
{"action":{"identity":{"address":"N\u0000sourcecred\u0000core\u0000IDENTITY\u00007kHRwjgb1SR8HzyUDm61jQ\u0000","aliases":[],"id":"7kHRwjgb1SR8HzyUDm61jQ","name":"JennyK","subtype":"USER"},"type":"CREATE_IDENTITY"},"ledgerTimestamp":1645405360001,"uuid":"Tju1KGM6YjQYdhZfLP6J1w","version":"1"}
{"action":{"alias":{"address":"N\u0000sourcecred\u0000discord\u0000MEMBER\u0000user\u0000802642216170160128\u0000","description":"discord/JennyK#9454"},"identityId":"7kHRwjgb1SR8HzyUDm61jQ","type":"ADD_ALIAS"},"ledgerTimestamp":1645405360001,"uuid":"uEnnelWUQTkmsRq52QdJqA","version":"1"}
{"action":{"identity":{"address":"N\u0000sourcecred\u0000core\u0000IDENTITY\u0000iXFxvAjKjlzrPtbh74m5bw\u0000","aliases":[],"id":"iXFxvAjKjlzrPtbh74m5bw","name":"daedelan","subtype":"USER"},"type":"CREATE_IDENTITY"},"ledgerTimestamp":1645405360001,"uuid":"t03aKzTGk35L44jU8h3QJA","version":"1"}
{"action":{"alias":{"address":"N\u0000sourcecred\u0000discord\u0000MEMBER\u0000user\u0000817949158732333056\u0000","description":"discord/daedelan#8161"},"identityId":"iXFxvAjKjlzrPtbh74m5bw","type":"ADD_ALIAS"},"ledgerTimestamp":1645405360001,"uuid":"i7Jc7S9fXbPT9umjgem3rQ","version":"1"}
{"action":{"identity":{"address":"N\u0000sourcecred\u0000core\u0000IDENTITY\u0000F90dgRHRKji5JCnS4UPtPQ\u0000","aliases":[],"id":"F90dgRHRKji5JCnS4UPtPQ","name":"ubuku--","subtype":"USER"},"type":"CREATE_IDENTITY"},"ledgerTimestamp":1645405360002,"uuid":"80tNXlgkxza5gyvyaIVcaA","version":"1"}
{"action":{"alias":{"address":"N\u0000sourcecred\u0000discord\u0000MEMBER\u0000user\u0000828188261209473035\u0000","description":"discord/ubuku--#4148"},"identityId":"F90dgRHRKji5JCnS4UPtPQ","type":"ADD_ALIAS"},"ledgerTimestamp":1645405360002,"uuid":"QmDqCgRvJhddlbpE7zWOdQ","version":"1"}
{"action":{"identity":{"address":"N\u0000sourcecred\u0000core\u0000IDENTITY\u00004Lzow2C19aXvWYW4bCAAsg\u0000","aliases":[],"id":"4Lzow2C19aXvWYW4bCAAsg","name":"Varunkothamachu","subtype":"USER"},"type":"CREATE_IDENTITY"},"ledgerTimestamp":1645405360002,"uuid":"zG2tahkYAqrRTaK8E5YqGQ","version":"1"}
{"action":{"alias":{"address":"N\u0000sourcecred\u0000discord\u0000MEMBER\u0000user\u0000855086717744185345\u0000","description":"discord/Varunkothamachu#8751"},"identityId":"4Lzow2C19aXvWYW4bCAAsg","type":"ADD_ALIAS"},"ledgerTimestamp":1645405360002,"uuid":"VYgDjRvCwF5KdGsJCm3B9Q","version":"1"}
{"action":{"identity":{"address":"N\u0000sourcecred\u0000core\u0000IDENTITY\u0000ySmKtgcqI3kGXqedmd3jQg\u0000","aliases":[],"id":"ySmKtgcqI3kGXqedmd3jQg","name":"geez","subtype":"USER"},"type":"CREATE_IDENTITY"},"ledgerTimestamp":1645405360002,"uuid":"r5BZuniVEN12uaMXYVwaOw","version":"1"}
{"action":{"alias":{"address":"N\u0000sourcecred\u0000discord\u0000MEMBER\u0000user\u0000883286295533723670\u0000","description":"discord/geez#3883"},"identityId":"ySmKtgcqI3kGXqedmd3jQg","type":"ADD_ALIAS"},"ledgerTimestamp":1645405360002,"uuid":"Zw65keQUqhbSr1dxZ0vRDw","version":"1"}
{"action":{"identity":{"address":"N\u0000sourcecred\u0000core\u0000IDENTITY\u0000JZrkd5Eby7GpG6qS7xoN5Q\u0000","aliases":[],"id":"JZrkd5Eby7GpG6qS7xoN5Q","name":"skoth","subtype":"USER"},"type":"CREATE_IDENTITY"},"ledgerTimestamp":1645405360003,"uuid":"XgGH2WzHDDiaVhRbMwdGrQ","version":"1"}
{"action":{"alias":{"address":"N\u0000sourcecred\u0000discord\u0000MEMBER\u0000user\u0000910935955324686439\u0000","description":"discord/skoth#8973"},"identityId":"JZrkd5Eby7GpG6qS7xoN5Q","type":"ADD_ALIAS"},"ledgerTimestamp":1645405360003,"uuid":"pNFZLaPsqRTnq44SoL535A","version":"1"}
{"action":{"identity":{"address":"N\u0000sourcecred\u0000core\u0000IDENTITY\u0000v4i94K4lytpyI9OgvNY9TA\u0000","aliases":[],"id":"v4i94K4lytpyI9OgvNY9TA","name":"sciaddict","subtype":"USER"},"type":"CREATE_IDENTITY"},"ledgerTimestamp":1645405360003,"uuid":"VR0IMWM5fYQAbCQDYFVm1g","version":"1"}
{"action":{"alias":{"address":"N\u0000sourcecred\u0000discord\u0000MEMBER\u0000user\u0000935375112499265566\u0000","description":"discord/sciaddict#8938"},"identityId":"v4i94K4lytpyI9OgvNY9TA","type":"ADD_ALIAS"},"ledgerTimestamp":1645405360004,"uuid":"pm7w6v9y3evW4DKQAVwn0Q","version":"1"}
{"action":{"identity":{"address":"N\u0000sourcecred\u0000core\u0000IDENTITY\u0000lqi4k50bOxdi1vKNnyyjkw\u0000","aliases":[],"id":"lqi4k50bOxdi1vKNnyyjkw","name":"shid","subtype":"USER"},"type":"CREATE_IDENTITY"},"ledgerTimestamp":1645405360004,"uuid":"Wh7LvFRKMxZ8Qkjt5Qn8DA","version":"1"}
{"action":{"alias":{"address":"N\u0000sourcecred\u0000discord\u0000MEMBER\u0000user\u0000165626765484490753\u0000","description":"discord/shid#2514"},"identityId":"lqi4k50bOxdi1vKNnyyjkw","type":"ADD_ALIAS"},"ledgerTimestamp":1645405360004,"uuid":"WlbnZUDAAJe9xH00xY1bmQ","version":"1"}
{"action":{"identity":{"address":"N\u0000sourcecred\u0000core\u0000IDENTITY\u0000FEho2a6ZbZ81BJbEib8oZQ\u0000","aliases":[],"id":"FEho2a6ZbZ81BJbEib8oZQ","name":"Sina-Iman","subtype":"USER"},"type":"CREATE_IDENTITY"},"ledgerTimestamp":1645405360004,"uuid":"GUOy52zM38mjXWOpOj5dWw","version":"1"}
{"action":{"alias":{"address":"N\u0000sourcecred\u0000discord\u0000MEMBER\u0000user\u0000192042086021726208\u0000","description":"discord/Sina-Iman#2897"},"identityId":"FEho2a6ZbZ81BJbEib8oZQ","type":"ADD_ALIAS"},"ledgerTimestamp":1645405360004,"uuid":"DXAmrS2Vlp3Mxq6ZGHN5lw","version":"1"}
{"action":{"identity":{"address":"N\u0000sourcecred\u0000core\u0000IDENTITY\u00005JBtaC8sm3Bw8zqXH6bdzA\u0000","aliases":[],"id":"5JBtaC8sm3Bw8zqXH6bdzA","name":"kabat","subtype":"USER"},"type":"CREATE_IDENTITY"},"ledgerTimestamp":1645405360005,"uuid":"4ptP4Zg2MpokibsJZyi3Wg","version":"1"}
{"action":{"alias":{"address":"N\u0000sourcecred\u0000discord\u0000MEMBER\u0000user\u0000204335630291959809\u0000","description":"discord/kabat#3484"},"identityId":"5JBtaC8sm3Bw8zqXH6bdzA","type":"ADD_ALIAS"},"ledgerTimestamp":1645405360005,"uuid":"QIA7dwW2Au2H4CJBpoRdEg","version":"1"}
{"action":{"identity":{"address":"N\u0000sourcecred\u0000core\u0000IDENTITY\u0000GL0orT6JDomMVqL14oIwng\u0000","aliases":[],"id":"GL0orT6JDomMVqL14oIwng","name":"with-heart","subtype":"USER"},"type":"CREATE_IDENTITY"},"ledgerTimestamp":1645405360005,"uuid":"vSGwaN4rFVHexFRud6LrTA","version":"1"}
{"action":{"alias":{"address":"N\u0000sourcecred\u0000discord\u0000MEMBER\u0000user\u0000256500797959831552\u0000","description":"discord/with-heart#0001"},"identityId":"GL0orT6JDomMVqL14oIwng","type":"ADD_ALIAS"},"ledgerTimestamp":1645405360005,"uuid":"6dj06tZyT6Vx5zcqfZFOog","version":"1"}
{"action":{"identity":{"address":"N\u0000sourcecred\u0000core\u0000IDENTITY\u0000lTRgWPoa1bQmTru5kOC9Dg\u0000","aliases":[],"id":"lTRgWPoa1bQmTru5kOC9Dg","name":"Zira","subtype":"BOT"},"type":"CREATE_IDENTITY"},"ledgerTimestamp":1645405360005,"uuid":"YkBFkwImEZ5PcKwxmWdrWw","version":"1"}
{"action":{"alias":{"address":"N\u0000sourcecred\u0000discord\u0000MEMBER\u0000bot\u0000275813801792634880\u0000","description":"discord/Zira#9472"},"identityId":"lTRgWPoa1bQmTru5kOC9Dg","type":"ADD_ALIAS"},"ledgerTimestamp":1645405360005,"uuid":"hO8W3Hxkp0egg5mA6vEh0g","version":"1"}
{"action":{"identity":{"address":"N\u0000sourcecred\u0000core\u0000IDENTITY\u00003kABKB47Amnqw6Mgk8W2QQ\u0000","aliases":[],"id":"3kABKB47Amnqw6Mgk8W2QQ","name":"willsputra---Gitcoin","subtype":"USER"},"type":"CREATE_IDENTITY"},"ledgerTimestamp":1645405360005,"uuid":"sMA4ergVoJ8yJ2mpYFBW8A","version":"1"}
{"action":{"alias":{"address":"N\u0000sourcecred\u0000discord\u0000MEMBER\u0000user\u0000375850432750157828\u0000","description":"discord/willsputra---Gitcoin#7177"},"identityId":"3kABKB47Amnqw6Mgk8W2QQ","type":"ADD_ALIAS"},"ledgerTimestamp":1645405360006,"uuid":"KOar3ktpkledl2hJhmGRvQ","version":"1"}
{"action":{"identity":{"address":"N\u0000sourcecred\u0000core\u0000IDENTITY\u0000ygLRRdhb9SR0KrZ7TMtKyg\u0000","aliases":[],"id":"ygLRRdhb9SR0KrZ7TMtKyg","name":"tobystic","subtype":"USER"},"type":"CREATE_IDENTITY"},"ledgerTimestamp":1645405360006,"uuid":"ZXUdkJPVmuARIrPB1x4OWQ","version":"1"}
{"action":{"alias":{"address":"N\u0000sourcecred\u0000discord\u0000MEMBER\u0000user\u0000514565183964839939\u0000","description":"discord/tobystic#5007"},"identityId":"ygLRRdhb9SR0KrZ7TMtKyg","type":"ADD_ALIAS"},"ledgerTimestamp":1645405360006,"uuid":"hlXrLNd3mcNnbhXjvdYdyA","version":"1"}
{"action":{"identity":{"address":"N\u0000sourcecred\u0000core\u0000IDENTITY\u0000ueaKnVB9wNB3QyH0MiXjbw\u0000","aliases":[],"id":"ueaKnVB9wNB3QyH0MiXjbw","name":"Chopras---42OPE","subtype":"USER"},"type":"CREATE_IDENTITY"},"ledgerTimestamp":1645405360006,"uuid":"Pmef1yLLVkY5j0NRwnZRpg","version":"1"}
{"action":{"alias":{"address":"N\u0000sourcecred\u0000discord\u0000MEMBER\u0000user\u0000537474612620034069\u0000","description":"discord/Chopras---42OPE#4998"},"identityId":"ueaKnVB9wNB3QyH0MiXjbw","type":"ADD_ALIAS"},"ledgerTimestamp":1645405360006,"uuid":"O6eeZ0nCBMYAo423U11Tdw","version":"1"}
{"action":{"identity":{"address":"N\u0000sourcecred\u0000core\u0000IDENTITY\u0000ArLl1DeZzrKKHpzSKFXXcQ\u0000","aliases":[],"id":"ArLl1DeZzrKKHpzSKFXXcQ","name":"Urek","subtype":"USER"},"type":"CREATE_IDENTITY"},"ledgerTimestamp":1645405360007,"uuid":"QACDF7WMazB0SDQIQlxTYg","version":"1"}
{"action":{"alias":{"address":"N\u0000sourcecred\u0000discord\u0000MEMBER\u0000user\u0000653878275902275615\u0000","description":"discord/Urek#5014"},"identityId":"ArLl1DeZzrKKHpzSKFXXcQ","type":"ADD_ALIAS"},"ledgerTimestamp":1645405360007,"uuid":"c3ySJXavSrReYlyRMY4HEw","version":"1"}
{"action":{"identity":{"address":"N\u0000sourcecred\u0000core\u0000IDENTITY\u0000XZbPa5LIyuRGkbFL3VE3qw\u0000","aliases":[],"id":"XZbPa5LIyuRGkbFL3VE3qw","name":"Jakub","subtype":"USER"},"type":"CREATE_IDENTITY"},"ledgerTimestamp":1645405360007,"uuid":"Vp92irA0zM61o6WyZ9aeRQ","version":"1"}
{"action":{"alias":{"address":"N\u0000sourcecred\u0000discord\u0000MEMBER\u0000user\u0000698615884889194587\u0000","description":"discord/Jakub#3317"},"identityId":"XZbPa5LIyuRGkbFL3VE3qw","type":"ADD_ALIAS"},"ledgerTimestamp":1645405360007,"uuid":"tzJ2B70H1jaxQ7D1uYxHbQ","version":"1"}
{"action":{"identity":{"address":"N\u0000sourcecred\u0000core\u0000IDENTITY\u0000wCBPdX6KGp0ee5V2ogOADg\u0000","aliases":[],"id":"wCBPdX6KGp0ee5V2ogOADg","name":"Nimi-Vashi","subtype":"USER"},"type":"CREATE_IDENTITY"},"ledgerTimestamp":1645405360008,"uuid":"UekMurIW9okM0aZTRrb5fw","version":"1"}
{"action":{"alias":{"address":"N\u0000sourcecred\u0000discord\u0000MEMBER\u0000user\u0000699013714317148210\u0000","description":"discord/Nimi-Vashi#8251"},"identityId":"wCBPdX6KGp0ee5V2ogOADg","type":"ADD_ALIAS"},"ledgerTimestamp":1645405360008,"uuid":"ESy3oPklFeGinD7QjRXfoQ","version":"1"}
{"action":{"identity":{"address":"N\u0000sourcecred\u0000core\u0000IDENTITY\u0000WR9IZcBMbz6DMU5mVEEqPg\u0000","aliases":[],"id":"WR9IZcBMbz6DMU5mVEEqPg","name":"nicklinck","subtype":"USER"},"type":"CREATE_IDENTITY"},"ledgerTimestamp":1645405360008,"uuid":"xvnqwj8B4kKkrOTO5djlxw","version":"1"}
{"action":{"alias":{"address":"N\u0000sourcecred\u0000discord\u0000MEMBER\u0000user\u0000783927840638369812\u0000","description":"discord/nicklinck#6691"},"identityId":"WR9IZcBMbz6DMU5mVEEqPg","type":"ADD_ALIAS"},"ledgerTimestamp":1645405360008,"uuid":"I83aEKHGSonmAIRsOinQrw","version":"1"}
{"action":{"identity":{"address":"N\u0000sourcecred\u0000core\u0000IDENTITY\u0000QPt3Z8yFZ8wiq0dZS1p5QQ\u0000","aliases":[],"id":"QPt3Z8yFZ8wiq0dZS1p5QQ","name":"nnsk","subtype":"USER"},"type":"CREATE_IDENTITY"},"ledgerTimestamp":1645405360008,"uuid":"BA41EboS5rEVj51LaQyloA","version":"1"}
{"action":{"alias":{"address":"N\u0000sourcecred\u0000discord\u0000MEMBER\u0000user\u0000819725310919442472\u0000","description":"discord/nnsk#4182"},"identityId":"QPt3Z8yFZ8wiq0dZS1p5QQ","type":"ADD_ALIAS"},"ledgerTimestamp":1645405360008,"uuid":"HDWwofVM4tQ0MEt3RqBraA","version":"1"}
{"action":{"identity":{"address":"N\u0000sourcecred\u0000core\u0000IDENTITY\u00005b3ulOzszQ0dugXMt1rGCg\u0000","aliases":[],"id":"5b3ulOzszQ0dugXMt1rGCg","name":"hirenbpatel","subtype":"USER"},"type":"CREATE_IDENTITY"},"ledgerTimestamp":1645405360009,"uuid":"iDtPD6nPyBXNHZKgDgCAZg","version":"1"}
{"action":{"alias":{"address":"N\u0000sourcecred\u0000discord\u0000MEMBER\u0000user\u0000910619382386925589\u0000","description":"discord/hirenbpatel#0914"},"identityId":"5b3ulOzszQ0dugXMt1rGCg","type":"ADD_ALIAS"},"ledgerTimestamp":1645405360009,"uuid":"6OHAdHxYcxFqYriNzRNtkw","version":"1"}
{"action":{"identity":{"address":"N\u0000sourcecred\u0000core\u0000IDENTITY\u00005ek9XLGdryHO2kLa0fltLw\u0000","aliases":[],"id":"5ek9XLGdryHO2kLa0fltLw","name":"carlaost","subtype":"USER"},"type":"CREATE_IDENTITY"},"ledgerTimestamp":1645405360009,"uuid":"tOrh4ziokJRcVw44DP5hYA","version":"1"}
{"action":{"alias":{"address":"N\u0000sourcecred\u0000discord\u0000MEMBER\u0000user\u0000910940211754700882\u0000","description":"discord/carlaost#5298"},"identityId":"5ek9XLGdryHO2kLa0fltLw","type":"ADD_ALIAS"},"ledgerTimestamp":1645405360009,"uuid":"Y3zKlK1b920HVQ5T804uXA","version":"1"}
{"action":{"identity":{"address":"N\u0000sourcecred\u0000core\u0000IDENTITY\u0000WC8H3nNj4mvFNAMeAvSz2Q\u0000","aliases":[],"id":"WC8H3nNj4mvFNAMeAvSz2Q","name":"laura314","subtype":"USER"},"type":"CREATE_IDENTITY"},"ledgerTimestamp":1645405360012,"uuid":"TwNIb4iWXx08kW7iLT9mLw","version":"1"}
{"action":{"alias":{"address":"N\u0000sourcecred\u0000discord\u0000MEMBER\u0000user\u0000921239888039391313\u0000","description":"discord/laura314#2123"},"identityId":"WC8H3nNj4mvFNAMeAvSz2Q","type":"ADD_ALIAS"},"ledgerTimestamp":1645405360012,"uuid":"KlOjXY5Hnzm4nQGXm7S2AQ","version":"1"}
