{"action":{"identity":{"address":"N\u0000sourcecred\u0000core\u0000IDENTITY\u0000qSqDm0yiViDHwDWhP6o7HA\u0000","aliases":[],"id":"qSqDm0yiViDHwDWhP6o7HA","name":"Ekkeharta","subtype":"USER"},"type":"CREATE_IDENTITY"},"ledgerTimestamp":1642096891703,"uuid":"uJD1lo61GEZoV8FwydqWfQ","version":"1"}
{"action":{"alias":{"address":"N\u0000sourcecred\u0000discord\u0000MEMBER\u0000user\u0000131942579985055744\u0000","description":"discord/Ekkeharta#3447"},"identityId":"qSqDm0yiViDHwDWhP6o7HA","type":"ADD_ALIAS"},"ledgerTimestamp":1642096891703,"uuid":"FBeCkTV7qQyopYXrcJVobQ","version":"1"}
{"action":{"identity":{"address":"N\u0000sourcecred\u0000core\u0000IDENTITY\u0000euW99YR9WlKvJi6Q1DVxQQ\u0000","aliases":[],"id":"euW99YR9WlKvJi6Q1DVxQQ","name":"Leyoric","subtype":"USER"},"type":"CREATE_IDENTITY"},"ledgerTimestamp":1642096891704,"uuid":"bZpR2OIMNArAkWBWqiGdqQ","version":"1"}
{"action":{"alias":{"address":"N\u0000sourcecred\u0000discord\u0000MEMBER\u0000user\u0000134423116959973378\u0000","description":"discord/Leyoric#9095"},"identityId":"euW99YR9WlKvJi6Q1DVxQQ","type":"ADD_ALIAS"},"ledgerTimestamp":1642096891704,"uuid":"ymZ1OOnS8pdjbAx4m9F82A","version":"1"}
{"action":{"identity":{"address":"N\u0000sourcecred\u0000core\u0000IDENTITY\u0000oNlPIDpeEMlkwL8UYtBr1g\u0000","aliases":[],"id":"oNlPIDpeEMlkwL8UYtBr1g","name":"HomicidalChicken","subtype":"USER"},"type":"CREATE_IDENTITY"},"ledgerTimestamp":1642096891704,"uuid":"QEyE09S8YoPmXd7GPvRwOg","version":"1"}
{"action":{"alias":{"address":"N\u0000sourcecred\u0000discord\u0000MEMBER\u0000user\u0000221288305222877185\u0000","description":"discord/HomicidalChicken#8326"},"identityId":"oNlPIDpeEMlkwL8UYtBr1g","type":"ADD_ALIAS"},"ledgerTimestamp":1642096891705,"uuid":"HJzj6kekvkIm5b0VQsveMQ","version":"1"}
{"action":{"identity":{"address":"N\u0000sourcecred\u0000core\u0000IDENTITY\u0000qcXYSMhDbKsRbWOq9E1lNA\u0000","aliases":[],"id":"qcXYSMhDbKsRbWOq9E1lNA","name":"Dank-Mona","subtype":"USER"},"type":"CREATE_IDENTITY"},"ledgerTimestamp":1642096891705,"uuid":"WurNk0FdbjLR8Nf8eI1j5g","version":"1"}
{"action":{"alias":{"address":"N\u0000sourcecred\u0000discord\u0000MEMBER\u0000user\u0000225311920754786304\u0000","description":"discord/Dank-Mona#4426"},"identityId":"qcXYSMhDbKsRbWOq9E1lNA","type":"ADD_ALIAS"},"ledgerTimestamp":1642096891705,"uuid":"x9MyTqCGei6jll0XztDDIA","version":"1"}
{"action":{"identity":{"address":"N\u0000sourcecred\u0000core\u0000IDENTITY\u0000AJIk0MDdXDflP7e7Jz11Eg\u0000","aliases":[],"id":"AJIk0MDdXDflP7e7Jz11Eg","name":"ufkhan97","subtype":"USER"},"type":"CREATE_IDENTITY"},"ledgerTimestamp":1642096891705,"uuid":"r1QcQo6ikdvuOxc6DdFwDg","version":"1"}
{"action":{"alias":{"address":"N\u0000sourcecred\u0000discord\u0000MEMBER\u0000user\u0000259178972301099008\u0000","description":"discord/ufkhan97#4345"},"identityId":"AJIk0MDdXDflP7e7Jz11Eg","type":"ADD_ALIAS"},"ledgerTimestamp":1642096891706,"uuid":"Nzj1Nh6CrWxrkcyHKE1Afw","version":"1"}
{"action":{"identity":{"address":"N\u0000sourcecred\u0000core\u0000IDENTITY\u0000abbugaXtn28tEHNXqL7LMg\u0000","aliases":[],"id":"abbugaXtn28tEHNXqL7LMg","name":"-BrianMillsJr","subtype":"USER"},"type":"CREATE_IDENTITY"},"ledgerTimestamp":1642096891706,"uuid":"R7OtXSaYVoC4BKrLqd405w","version":"1"}
{"action":{"alias":{"address":"N\u0000sourcecred\u0000discord\u0000MEMBER\u0000user\u0000325811370195156994\u0000","description":"discord/-BrianMillsJr#5987"},"identityId":"abbugaXtn28tEHNXqL7LMg","type":"ADD_ALIAS"},"ledgerTimestamp":1642096891706,"uuid":"2R3nrwEgdXw8yxJ8pvDNFg","version":"1"}
{"action":{"identity":{"address":"N\u0000sourcecred\u0000core\u0000IDENTITY\u0000emc7HZr0xE74N4L7ZEYLDQ\u0000","aliases":[],"id":"emc7HZr0xE74N4L7ZEYLDQ","name":"crossoveranx","subtype":"USER"},"type":"CREATE_IDENTITY"},"ledgerTimestamp":1642096891706,"uuid":"4BcnAZBapJoyq3sM79nyJA","version":"1"}
{"action":{"alias":{"address":"N\u0000sourcecred\u0000discord\u0000MEMBER\u0000user\u0000379030669201768448\u0000","description":"discord/crossoveranx#1832"},"identityId":"emc7HZr0xE74N4L7ZEYLDQ","type":"ADD_ALIAS"},"ledgerTimestamp":1642096891706,"uuid":"MiLhXmIbrX3fERBsdaWLEw","version":"1"}
{"action":{"identity":{"address":"N\u0000sourcecred\u0000core\u0000IDENTITY\u0000b3RQ7kRgN57eWx70SpO4YA\u0000","aliases":[],"id":"b3RQ7kRgN57eWx70SpO4YA","name":"Keturin","subtype":"USER"},"type":"CREATE_IDENTITY"},"ledgerTimestamp":1642096891706,"uuid":"ok9k966R6BMvbz93RyLDDw","version":"1"}
{"action":{"alias":{"address":"N\u0000sourcecred\u0000discord\u0000MEMBER\u0000user\u0000455016695174529025\u0000","description":"discord/Keturin#6669"},"identityId":"b3RQ7kRgN57eWx70SpO4YA","type":"ADD_ALIAS"},"ledgerTimestamp":1642096891706,"uuid":"OmzYNhz0aM0rYoq0ptXDpQ","version":"1"}
{"action":{"identity":{"address":"N\u0000sourcecred\u0000core\u0000IDENTITY\u0000ZLOW51V8UnpfQDJFKByzlg\u0000","aliases":[],"id":"ZLOW51V8UnpfQDJFKByzlg","name":"llllvvuu","subtype":"USER"},"type":"CREATE_IDENTITY"},"ledgerTimestamp":1642096891707,"uuid":"Bv7qI2gX5qBTexhGl7w3JA","version":"1"}
{"action":{"alias":{"address":"N\u0000sourcecred\u0000discord\u0000MEMBER\u0000user\u0000522402421566078978\u0000","description":"discord/llllvvuu#1782"},"identityId":"ZLOW51V8UnpfQDJFKByzlg","type":"ADD_ALIAS"},"ledgerTimestamp":1642096891707,"uuid":"Wh5FKKuZY14zVZwopdYr6g","version":"1"}
{"action":{"identity":{"address":"N\u0000sourcecred\u0000core\u0000IDENTITY\u0000nmAHnsxJ4nXbWlf9g8U41A\u0000","aliases":[],"id":"nmAHnsxJ4nXbWlf9g8U41A","name":"Mike-Elias","subtype":"USER"},"type":"CREATE_IDENTITY"},"ledgerTimestamp":1642096891707,"uuid":"BvasLlKdLXMGy7wgM7zH9A","version":"1"}
{"action":{"alias":{"address":"N\u0000sourcecred\u0000discord\u0000MEMBER\u0000user\u0000626178021120016395\u0000","description":"discord/Mike-Elias#4724"},"identityId":"nmAHnsxJ4nXbWlf9g8U41A","type":"ADD_ALIAS"},"ledgerTimestamp":1642096891707,"uuid":"Mm1vxlmoeokCdwgbQwb37w","version":"1"}
{"action":{"identity":{"address":"N\u0000sourcecred\u0000core\u0000IDENTITY\u000039N9YIQ3WwDTGmk2w2uLBg\u0000","aliases":[],"id":"39N9YIQ3WwDTGmk2w2uLBg","name":"Shamburgularara---XXI","subtype":"USER"},"type":"CREATE_IDENTITY"},"ledgerTimestamp":1642096891707,"uuid":"BPO41AdIjulIRFNVlQnMow","version":"1"}
{"action":{"alias":{"address":"N\u0000sourcecred\u0000discord\u0000MEMBER\u0000user\u0000718139779509911623\u0000","description":"discord/Shamburgularara---XXI#7217"},"identityId":"39N9YIQ3WwDTGmk2w2uLBg","type":"ADD_ALIAS"},"ledgerTimestamp":1642096891707,"uuid":"9DP885uQegZ23maBj4idwA","version":"1"}
{"action":{"identity":{"address":"N\u0000sourcecred\u0000core\u0000IDENTITY\u0000zH9ndQ4KkmMQmCAYDYUjwQ\u0000","aliases":[],"id":"zH9ndQ4KkmMQmCAYDYUjwQ","name":"darren","subtype":"USER"},"type":"CREATE_IDENTITY"},"ledgerTimestamp":1642096891707,"uuid":"899Sx46Swn4tL5ulrzaqzA","version":"1"}
{"action":{"alias":{"address":"N\u0000sourcecred\u0000discord\u0000MEMBER\u0000user\u0000852800209611653120\u0000","description":"discord/darren#1994"},"identityId":"zH9ndQ4KkmMQmCAYDYUjwQ","type":"ADD_ALIAS"},"ledgerTimestamp":1642096891707,"uuid":"Eph3h6HNwlK8wQntXBqh0Q","version":"1"}
{"action":{"identity":{"address":"N\u0000sourcecred\u0000core\u0000IDENTITY\u00004xAvDI2FlIDrq5yNYyggQw\u0000","aliases":[],"id":"4xAvDI2FlIDrq5yNYyggQw","name":"tone123456789","subtype":"USER"},"type":"CREATE_IDENTITY"},"ledgerTimestamp":1642096891708,"uuid":"KLm6QupP7AtRPVrImxUK7w","version":"1"}
{"action":{"alias":{"address":"N\u0000sourcecred\u0000discord\u0000MEMBER\u0000user\u0000902331794387533864\u0000","description":"discord/tone123456789#6303"},"identityId":"4xAvDI2FlIDrq5yNYyggQw","type":"ADD_ALIAS"},"ledgerTimestamp":1642096891708,"uuid":"d8VeFXAsZcLjH0zb6uyU3g","version":"1"}
{"action":{"identity":{"address":"N\u0000sourcecred\u0000core\u0000IDENTITY\u0000Pe6A0Kl0e6xwjb29MQ7rig\u0000","aliases":[],"id":"Pe6A0Kl0e6xwjb29MQ7rig","name":"sam76021","subtype":"USER"},"type":"CREATE_IDENTITY"},"ledgerTimestamp":1642096891708,"uuid":"bsE1W3qAdXWLIzi6jHggWw","version":"1"}
{"action":{"alias":{"address":"N\u0000sourcecred\u0000discord\u0000MEMBER\u0000user\u0000905595868768501831\u0000","description":"discord/sam76021#2389"},"identityId":"Pe6A0Kl0e6xwjb29MQ7rig","type":"ADD_ALIAS"},"ledgerTimestamp":1642096891708,"uuid":"FjqaLu4yKIev988ecaCO2w","version":"1"}
{"action":{"identity":{"address":"N\u0000sourcecred\u0000core\u0000IDENTITY\u0000W3w8X7cGwvt7fp5XrVskag\u0000","aliases":[],"id":"W3w8X7cGwvt7fp5XrVskag","name":"versusmikehistory","subtype":"USER"},"type":"CREATE_IDENTITY"},"ledgerTimestamp":1642096891708,"uuid":"DIQDRO7gQIK8U1xWJ7HPrA","version":"1"}
{"action":{"alias":{"address":"N\u0000sourcecred\u0000discord\u0000MEMBER\u0000user\u0000921920605400469554\u0000","description":"discord/versusmikehistory#0363"},"identityId":"W3w8X7cGwvt7fp5XrVskag","type":"ADD_ALIAS"},"ledgerTimestamp":1642096891708,"uuid":"DRtDai1GF3H8r4hlEbOUQw","version":"1"}
{"action":{"identity":{"address":"N\u0000sourcecred\u0000core\u0000IDENTITY\u0000qkGQO5ba65R7h0J1SxK2fA\u0000","aliases":[],"id":"qkGQO5ba65R7h0J1SxK2fA","name":"SourceCred-Braid-Bot","subtype":"BOT"},"type":"CREATE_IDENTITY"},"ledgerTimestamp":1642096891708,"uuid":"WBjxPZLl23rJmBAJQKMwHA","version":"1"}
{"action":{"alias":{"address":"N\u0000sourcecred\u0000discord\u0000MEMBER\u0000bot\u0000930561335492767744\u0000","description":"discord/SourceCred-Braid-Bot#3393"},"identityId":"qkGQO5ba65R7h0J1SxK2fA","type":"ADD_ALIAS"},"ledgerTimestamp":1642096891708,"uuid":"YoNbUrCEGzK1UVS8Zg7Zsg","version":"1"}
{"action":{"identity":{"address":"N\u0000sourcecred\u0000core\u0000IDENTITY\u0000rp9eJcE639XgmVT1V6sj7g\u0000","aliases":[],"id":"rp9eJcE639XgmVT1V6sj7g","name":"decentralion","subtype":"USER"},"type":"CREATE_IDENTITY"},"ledgerTimestamp":1642096892188,"uuid":"soGUO3M78XZ8z56A77HGIw","version":"1"}
{"action":{"alias":{"address":"N\u0000sourcecred\u0000github\u0000USERLIKE\u0000USER\u0000decentralion\u0000","description":"github/[@decentralion](https://github.com/decentralion)"},"identityId":"rp9eJcE639XgmVT1V6sj7g","type":"ADD_ALIAS"},"ledgerTimestamp":1642096892188,"uuid":"OkaBJYG6ioRi4idyZfL9OA","version":"1"}
{"action":{"identity":{"address":"N\u0000sourcecred\u0000core\u0000IDENTITY\u0000ZIGr9w3s1sxLCpSphMqqlg\u0000","aliases":[],"id":"ZIGr9w3s1sxLCpSphMqqlg","name":"credbot","subtype":"BOT"},"type":"CREATE_IDENTITY"},"ledgerTimestamp":1642096892188,"uuid":"zbupbPndX205W194t1KA2Q","version":"1"}
{"action":{"alias":{"address":"N\u0000sourcecred\u0000github\u0000USERLIKE\u0000BOT\u0000credbot\u0000","description":"github/[@credbot](https://github.com/credbot)"},"identityId":"ZIGr9w3s1sxLCpSphMqqlg","type":"ADD_ALIAS"},"ledgerTimestamp":1642096892188,"uuid":"RXQu0WwO5PIj9Ij2SlBTYg","version":"1"}
{"action":{"identity":{"address":"N\u0000sourcecred\u0000core\u0000IDENTITY\u0000Vt2674qUGfxL5ZezDTVrzA\u0000","aliases":[],"id":"Vt2674qUGfxL5ZezDTVrzA","name":"wchargin","subtype":"USER"},"type":"CREATE_IDENTITY"},"ledgerTimestamp":1642096892189,"uuid":"Cx6ieppR8o8WWJeXcvpKyg","version":"1"}
{"action":{"alias":{"address":"N\u0000sourcecred\u0000github\u0000USERLIKE\u0000USER\u0000wchargin\u0000","description":"github/[@wchargin](https://github.com/wchargin)"},"identityId":"Vt2674qUGfxL5ZezDTVrzA","type":"ADD_ALIAS"},"ledgerTimestamp":1642096892189,"uuid":"9DXbBeEMJ4DHmWYSKdJaAQ","version":"1"}
{"action":{"identity":{"address":"N\u0000sourcecred\u0000core\u0000IDENTITY\u0000ta1ouAqKPYSnb0BK3aoFxA\u0000","aliases":[],"id":"ta1ouAqKPYSnb0BK3aoFxA","name":"SourceCred","subtype":"PROJECT"},"type":"CREATE_IDENTITY"},"ledgerTimestamp":1642096892261,"uuid":"RRl4wmMEP0pj42aVuaVNKA","version":"1"}
{"action":{"identityId":"ta1ouAqKPYSnb0BK3aoFxA","type":"TOGGLE_ACTIVATION"},"ledgerTimestamp":1642096892261,"uuid":"g67m66hMCpA90jqlWx7YHA","version":"1"}
{"action":{"identity":{"address":"N\u0000sourcecred\u0000core\u0000IDENTITY\u0000Ei5Sei8lbrky5HzpRm2ZkA\u0000","aliases":[],"id":"Ei5Sei8lbrky5HzpRm2ZkA","name":"yung-calibri","subtype":"USER"},"type":"CREATE_IDENTITY"},"ledgerTimestamp":1647738965052,"uuid":"7Wg0puJPUEwu7rPV3JZ2jg","version":"1"}
{"action":{"alias":{"address":"N\u0000sourcecred\u0000discord\u0000MEMBER\u0000user\u0000132055527504084992\u0000","description":"discord/yung-calibri#0225"},"identityId":"Ei5Sei8lbrky5HzpRm2ZkA","type":"ADD_ALIAS"},"ledgerTimestamp":1647738965053,"uuid":"6ZkLSoDWJOP5NUAkCMgv5Q","version":"1"}
{"action":{"identity":{"address":"N\u0000sourcecred\u0000core\u0000IDENTITY\u0000kK66nWeHYotptdA4M8iRpg\u0000","aliases":[],"id":"kK66nWeHYotptdA4M8iRpg","name":"LaRiccia","subtype":"USER"},"type":"CREATE_IDENTITY"},"ledgerTimestamp":1647738965054,"uuid":"G81wqixcRQoyjOzpQuygKA","version":"1"}
{"action":{"alias":{"address":"N\u0000sourcecred\u0000discord\u0000MEMBER\u0000user\u0000193041322150461440\u0000","description":"discord/LaRiccia#6314"},"identityId":"kK66nWeHYotptdA4M8iRpg","type":"ADD_ALIAS"},"ledgerTimestamp":1647738965054,"uuid":"txVroo8EzrZJzrvAESANSw","version":"1"}
{"action":{"identity":{"address":"N\u0000sourcecred\u0000core\u0000IDENTITY\u00003t3SRB6QCBYzC2PT0RYZHw\u0000","aliases":[],"id":"3t3SRB6QCBYzC2PT0RYZHw","name":"rabage","subtype":"USER"},"type":"CREATE_IDENTITY"},"ledgerTimestamp":1647738965054,"uuid":"jsPM6pKcqqqRROLtRu0r0g","version":"1"}
{"action":{"alias":{"address":"N\u0000sourcecred\u0000discord\u0000MEMBER\u0000user\u0000220712729172770816\u0000","description":"discord/rabage#0897"},"identityId":"3t3SRB6QCBYzC2PT0RYZHw","type":"ADD_ALIAS"},"ledgerTimestamp":1647738965054,"uuid":"H3l7E8G6n4HqRzRK5kiVWg","version":"1"}
{"action":{"identity":{"address":"N\u0000sourcecred\u0000core\u0000IDENTITY\u00006vejHd11Ytx1U6sBONYalg\u0000","aliases":[],"id":"6vejHd11Ytx1U6sBONYalg","name":"chicken-sharoofi","subtype":"USER"},"type":"CREATE_IDENTITY"},"ledgerTimestamp":1647738965055,"uuid":"XKhZ0LF2BTKhV0GXkmuXAQ","version":"1"}
{"action":{"alias":{"address":"N\u0000sourcecred\u0000discord\u0000MEMBER\u0000user\u0000341767134495375363\u0000","description":"discord/chicken-sharoofi#4385"},"identityId":"6vejHd11Ytx1U6sBONYalg","type":"ADD_ALIAS"},"ledgerTimestamp":1647738965055,"uuid":"4h3GzUggo2KopOEujePD9w","version":"1"}
{"action":{"identity":{"address":"N\u0000sourcecred\u0000core\u0000IDENTITY\u0000ZI6kXBRFy6S9twoDHpcYPA\u0000","aliases":[],"id":"ZI6kXBRFy6S9twoDHpcYPA","name":"MantisClone","subtype":"USER"},"type":"CREATE_IDENTITY"},"ledgerTimestamp":1647738965055,"uuid":"WhlNyrVWUXTYrL9BNtqPHQ","version":"1"}
{"action":{"alias":{"address":"N\u0000sourcecred\u0000discord\u0000MEMBER\u0000user\u0000369700858742571008\u0000","description":"discord/MantisClone#2619"},"identityId":"ZI6kXBRFy6S9twoDHpcYPA","type":"ADD_ALIAS"},"ledgerTimestamp":1647738965055,"uuid":"lI1ATKAqi354u651bZYI1g","version":"1"}
{"action":{"identity":{"address":"N\u0000sourcecred\u0000core\u0000IDENTITY\u0000GAS0Qbbiys6pi9MMXGRYYw\u0000","aliases":[],"id":"GAS0Qbbiys6pi9MMXGRYYw","name":"heintess","subtype":"USER"},"type":"CREATE_IDENTITY"},"ledgerTimestamp":1647738965056,"uuid":"wv93mdMVMzTpOKar7FQRhA","version":"1"}
{"action":{"alias":{"address":"N\u0000sourcecred\u0000discord\u0000MEMBER\u0000user\u0000398278221319372801\u0000","description":"discord/heintess#7769"},"identityId":"GAS0Qbbiys6pi9MMXGRYYw","type":"ADD_ALIAS"},"ledgerTimestamp":1647738965056,"uuid":"E58Ja9c7lbiwdCxs4Evf4g","version":"1"}
{"action":{"identity":{"address":"N\u0000sourcecred\u0000core\u0000IDENTITY\u0000zDhvDWdSEpgKlnfbbvY89A\u0000","aliases":[],"id":"zDhvDWdSEpgKlnfbbvY89A","name":"JB87","subtype":"USER"},"type":"CREATE_IDENTITY"},"ledgerTimestamp":1647738965056,"uuid":"zdH7kJmexr4g2odSM3yP1g","version":"1"}
{"action":{"alias":{"address":"N\u0000sourcecred\u0000discord\u0000MEMBER\u0000user\u0000400321205724512267\u0000","description":"discord/JB87#8474"},"identityId":"zDhvDWdSEpgKlnfbbvY89A","type":"ADD_ALIAS"},"ledgerTimestamp":1647738965056,"uuid":"VMDpuxD2S11pGkwoDoFQuA","version":"1"}
{"action":{"identity":{"address":"N\u0000sourcecred\u0000core\u0000IDENTITY\u0000mm736XV5CNNxGyJvaBCWHg\u0000","aliases":[],"id":"mm736XV5CNNxGyJvaBCWHg","name":"rush0","subtype":"USER"},"type":"CREATE_IDENTITY"},"ledgerTimestamp":1647738965056,"uuid":"9diNTA3wk0FXS221IxCl8Q","version":"1"}
{"action":{"alias":{"address":"N\u0000sourcecred\u0000discord\u0000MEMBER\u0000user\u0000409745838441758721\u0000","description":"discord/rush0#5067"},"identityId":"mm736XV5CNNxGyJvaBCWHg","type":"ADD_ALIAS"},"ledgerTimestamp":1647738965057,"uuid":"v7wA8FdhWQXRPYqMXRCeYQ","version":"1"}
{"action":{"identity":{"address":"N\u0000sourcecred\u0000core\u0000IDENTITY\u0000w7HqBdI7o9aTduQXuN8qWw\u0000","aliases":[],"id":"w7HqBdI7o9aTduQXuN8qWw","name":"bestape","subtype":"USER"},"type":"CREATE_IDENTITY"},"ledgerTimestamp":1647738965057,"uuid":"Lt9oNx6zTE6OakMNd0AIXw","version":"1"}
{"action":{"alias":{"address":"N\u0000sourcecred\u0000discord\u0000MEMBER\u0000user\u0000476451739516534799\u0000","description":"discord/bestape#3069"},"identityId":"w7HqBdI7o9aTduQXuN8qWw","type":"ADD_ALIAS"},"ledgerTimestamp":1647738965057,"uuid":"2Lj5hO3K3tWlzrC95VdyfA","version":"1"}
{"action":{"identity":{"address":"N\u0000sourcecred\u0000core\u0000IDENTITY\u0000b6Tlf3wa8Vx39KZqugaLOA\u0000","aliases":[],"id":"b6Tlf3wa8Vx39KZqugaLOA","name":"GuavaGabriel","subtype":"USER"},"type":"CREATE_IDENTITY"},"ledgerTimestamp":1647738965058,"uuid":"nRS2MYaRIMla9DBKdHoZxg","version":"1"}
{"action":{"alias":{"address":"N\u0000sourcecred\u0000discord\u0000MEMBER\u0000user\u0000579305699281207307\u0000","description":"discord/GuavaGabriel#6530"},"identityId":"b6Tlf3wa8Vx39KZqugaLOA","type":"ADD_ALIAS"},"ledgerTimestamp":1647738965058,"uuid":"SgUL6hXf031zZI1bI9LgHg","version":"1"}
{"action":{"identity":{"address":"N\u0000sourcecred\u0000core\u0000IDENTITY\u000094Q76S3H0e8pHXIXKw9TZQ\u0000","aliases":[],"id":"94Q76S3H0e8pHXIXKw9TZQ","name":"eugene---SCRF","subtype":"USER"},"type":"CREATE_IDENTITY"},"ledgerTimestamp":1647738965058,"uuid":"cYqWUlAG3YkPW03t6xWgAA","version":"1"}
{"action":{"alias":{"address":"N\u0000sourcecred\u0000discord\u0000MEMBER\u0000user\u0000620452002425470977\u0000","description":"discord/eugene---SCRF#1706"},"identityId":"94Q76S3H0e8pHXIXKw9TZQ","type":"ADD_ALIAS"},"ledgerTimestamp":1647738965058,"uuid":"d0OUkycdG58wwRoZ0UByNg","version":"1"}
{"action":{"identity":{"address":"N\u0000sourcecred\u0000core\u0000IDENTITY\u0000KoA0wURCnx7ezR5hGl34kA\u0000","aliases":[],"id":"KoA0wURCnx7ezR5hGl34kA","name":"hebbianloop","subtype":"USER"},"type":"CREATE_IDENTITY"},"ledgerTimestamp":1647738965058,"uuid":"JQD3N7kEovNiN13C7MdsYw","version":"1"}
{"action":{"alias":{"address":"N\u0000sourcecred\u0000discord\u0000MEMBER\u0000user\u0000646837640980856862\u0000","description":"discord/hebbianloop#5169"},"identityId":"KoA0wURCnx7ezR5hGl34kA","type":"ADD_ALIAS"},"ledgerTimestamp":1647738965059,"uuid":"e6soRxGaxMOLI67GWbiayA","version":"1"}
{"action":{"identity":{"address":"N\u0000sourcecred\u0000core\u0000IDENTITY\u0000VEVmr132GeS3f5uG0eiJow\u0000","aliases":[],"id":"VEVmr132GeS3f5uG0eiJow","name":"Craig","subtype":"USER"},"type":"CREATE_IDENTITY"},"ledgerTimestamp":1647738965059,"uuid":"Ykl9jX21idI1tjz5Qq3bTw","version":"1"}
{"action":{"alias":{"address":"N\u0000sourcecred\u0000discord\u0000MEMBER\u0000user\u0000655144629481635841\u0000","description":"discord/Craig#0979"},"identityId":"VEVmr132GeS3f5uG0eiJow","type":"ADD_ALIAS"},"ledgerTimestamp":1647738965059,"uuid":"MpmTZYyPWaqPowZGFNESaw","version":"1"}
{"action":{"identity":{"address":"N\u0000sourcecred\u0000core\u0000IDENTITY\u00008os4V3IdaHBoadr3PxRBXQ\u0000","aliases":[],"id":"8os4V3IdaHBoadr3PxRBXQ","name":"Xena","subtype":"USER"},"type":"CREATE_IDENTITY"},"ledgerTimestamp":1647738965059,"uuid":"mIptGUG2JAXLNeZ0v1MyBw","version":"1"}
{"action":{"alias":{"address":"N\u0000sourcecred\u0000discord\u0000MEMBER\u0000user\u0000690682149195481268\u0000","description":"discord/Xena#1289"},"identityId":"8os4V3IdaHBoadr3PxRBXQ","type":"ADD_ALIAS"},"ledgerTimestamp":1647738965059,"uuid":"4dxgAkOi0Iw5anmdjb9eHg","version":"1"}
{"action":{"identity":{"address":"N\u0000sourcecred\u0000core\u0000IDENTITY\u0000rUkr3jNvdD9kVEmuEAzweQ\u0000","aliases":[],"id":"rUkr3jNvdD9kVEmuEAzweQ","name":"dvwz","subtype":"USER"},"type":"CREATE_IDENTITY"},"ledgerTimestamp":1647738965059,"uuid":"e75O5NKRQFLn1p6RQSnaig","version":"1"}
{"action":{"alias":{"address":"N\u0000sourcecred\u0000discord\u0000MEMBER\u0000user\u0000707869170657919027\u0000","description":"discord/dvwz#7836"},"identityId":"rUkr3jNvdD9kVEmuEAzweQ","type":"ADD_ALIAS"},"ledgerTimestamp":1647738965059,"uuid":"dxuz1SM16CpwL9spek9FQQ","version":"1"}
{"action":{"identity":{"address":"N\u0000sourcecred\u0000core\u0000IDENTITY\u0000j7qq3DYilcYT9053A4bPRQ\u0000","aliases":[],"id":"j7qq3DYilcYT9053A4bPRQ","name":"dnlmc","subtype":"USER"},"type":"CREATE_IDENTITY"},"ledgerTimestamp":1647738965060,"uuid":"HA1hAqFG9O639luv74TdOA","version":"1"}
{"action":{"alias":{"address":"N\u0000sourcecred\u0000discord\u0000MEMBER\u0000user\u0000709960689682350150\u0000","description":"discord/dnlmc#6862"},"identityId":"j7qq3DYilcYT9053A4bPRQ","type":"ADD_ALIAS"},"ledgerTimestamp":1647738965060,"uuid":"3kxDiZ3oNkbGvKOsmHVl6w","version":"1"}
{"action":{"identity":{"address":"N\u0000sourcecred\u0000core\u0000IDENTITY\u00003U3EQzVWdvp1xW8Bs48pPw\u0000","aliases":[],"id":"3U3EQzVWdvp1xW8Bs48pPw","name":"Jessica-Sacher","subtype":"USER"},"type":"CREATE_IDENTITY"},"ledgerTimestamp":1647738965061,"uuid":"4tj9YEPyYgQieWrjnwjeXg","version":"1"}
{"action":{"alias":{"address":"N\u0000sourcecred\u0000discord\u0000MEMBER\u0000user\u0000740984621482901546\u0000","description":"discord/Jessica-Sacher#8232"},"identityId":"3U3EQzVWdvp1xW8Bs48pPw","type":"ADD_ALIAS"},"ledgerTimestamp":1647738965061,"uuid":"bXagOv7njxZSoBcXXglS6A","version":"1"}
{"action":{"identity":{"address":"N\u0000sourcecred\u0000core\u0000IDENTITY\u0000ugQTmK2aotJuvmTR3mDeWg\u0000","aliases":[],"id":"ugQTmK2aotJuvmTR3mDeWg","name":"JennyK","subtype":"USER"},"type":"CREATE_IDENTITY"},"ledgerTimestamp":1647738965061,"uuid":"Aoe9fj1g4sazJF5IPUeGpw","version":"1"}
{"action":{"alias":{"address":"N\u0000sourcecred\u0000discord\u0000MEMBER\u0000user\u0000802642216170160128\u0000","description":"discord/JennyK#9454"},"identityId":"ugQTmK2aotJuvmTR3mDeWg","type":"ADD_ALIAS"},"ledgerTimestamp":1647738965061,"uuid":"TlCm3OTm5HPX58Puzm1e5Q","version":"1"}
{"action":{"identity":{"address":"N\u0000sourcecred\u0000core\u0000IDENTITY\u0000X6jG7enlKcPf821rKtLjFw\u0000","aliases":[],"id":"X6jG7enlKcPf821rKtLjFw","name":"daedelan","subtype":"USER"},"type":"CREATE_IDENTITY"},"ledgerTimestamp":1647738965061,"uuid":"FB21lqxAmIqFYTBvxNVAvw","version":"1"}
{"action":{"alias":{"address":"N\u0000sourcecred\u0000discord\u0000MEMBER\u0000user\u0000817949158732333056\u0000","description":"discord/daedelan#8161"},"identityId":"X6jG7enlKcPf821rKtLjFw","type":"ADD_ALIAS"},"ledgerTimestamp":1647738965061,"uuid":"jaIbfDJGEOZrhnSLp4ALDA","version":"1"}
{"action":{"identity":{"address":"N\u0000sourcecred\u0000core\u0000IDENTITY\u0000eViqxF4RX6bEW4cd0hXElg\u0000","aliases":[],"id":"eViqxF4RX6bEW4cd0hXElg","name":"ubuku--","subtype":"USER"},"type":"CREATE_IDENTITY"},"ledgerTimestamp":1647738965061,"uuid":"7QHdoq8D2qugRyvMykMXSA","version":"1"}
{"action":{"alias":{"address":"N\u0000sourcecred\u0000discord\u0000MEMBER\u0000user\u0000828188261209473035\u0000","description":"discord/ubuku--#4148"},"identityId":"eViqxF4RX6bEW4cd0hXElg","type":"ADD_ALIAS"},"ledgerTimestamp":1647738965061,"uuid":"OBbMpZj16Mvxo7FKfyYl5A","version":"1"}
{"action":{"identity":{"address":"N\u0000sourcecred\u0000core\u0000IDENTITY\u0000k70ZrleEG4LsByUAMqfj3A\u0000","aliases":[],"id":"k70ZrleEG4LsByUAMqfj3A","name":"Varunkothamachu","subtype":"USER"},"type":"CREATE_IDENTITY"},"ledgerTimestamp":1647738965062,"uuid":"6ZqVECrMiD6zCGlpgYmfNw","version":"1"}
{"action":{"alias":{"address":"N\u0000sourcecred\u0000discord\u0000MEMBER\u0000user\u0000855086717744185345\u0000","description":"discord/Varunkothamachu#8751"},"identityId":"k70ZrleEG4LsByUAMqfj3A","type":"ADD_ALIAS"},"ledgerTimestamp":1647738965062,"uuid":"mbWY9P6ZNxv715AZ6o0E5A","version":"1"}
{"action":{"identity":{"address":"N\u0000sourcecred\u0000core\u0000IDENTITY\u00005Q9hBcQQaAU53vBYdY0ZpQ\u0000","aliases":[],"id":"5Q9hBcQQaAU53vBYdY0ZpQ","name":"geez","subtype":"USER"},"type":"CREATE_IDENTITY"},"ledgerTimestamp":1647738965063,"uuid":"jJuKkKC5ONXeFmjrDnpabA","version":"1"}
{"action":{"alias":{"address":"N\u0000sourcecred\u0000discord\u0000MEMBER\u0000user\u0000883286295533723670\u0000","description":"discord/geez#3883"},"identityId":"5Q9hBcQQaAU53vBYdY0ZpQ","type":"ADD_ALIAS"},"ledgerTimestamp":1647738965063,"uuid":"oxmtrJXAlce8EAYBK46sLA","version":"1"}
{"action":{"identity":{"address":"N\u0000sourcecred\u0000core\u0000IDENTITY\u0000OyhDI3tZPs5BgJROBDei1w\u0000","aliases":[],"id":"OyhDI3tZPs5BgJROBDei1w","name":"skoth","subtype":"USER"},"type":"CREATE_IDENTITY"},"ledgerTimestamp":1647738965063,"uuid":"Vhe9vqS9mcmhRX4fEKNxYA","version":"1"}
{"action":{"alias":{"address":"N\u0000sourcecred\u0000discord\u0000MEMBER\u0000user\u0000910935955324686439\u0000","description":"discord/skoth#8973"},"identityId":"OyhDI3tZPs5BgJROBDei1w","type":"ADD_ALIAS"},"ledgerTimestamp":1647738965063,"uuid":"6WsOQ1s0ZV8BdU3RNgGsWA","version":"1"}
{"action":{"identity":{"address":"N\u0000sourcecred\u0000core\u0000IDENTITY\u0000JF2mE7Bskh7QyEuld9QOIw\u0000","aliases":[],"id":"JF2mE7Bskh7QyEuld9QOIw","name":"sciaddict","subtype":"USER"},"type":"CREATE_IDENTITY"},"ledgerTimestamp":1647738965063,"uuid":"LUzIMMhzrCEMI2gIrZ1kgw","version":"1"}
{"action":{"alias":{"address":"N\u0000sourcecred\u0000discord\u0000MEMBER\u0000user\u0000935375112499265566\u0000","description":"discord/sciaddict#8938"},"identityId":"JF2mE7Bskh7QyEuld9QOIw","type":"ADD_ALIAS"},"ledgerTimestamp":1647738965063,"uuid":"0bhyI8xjOesetwD5t69FZQ","version":"1"}
{"action":{"identity":{"address":"N\u0000sourcecred\u0000core\u0000IDENTITY\u0000OZyyZQMNiP3fbYBQ6SnF4w\u0000","aliases":[],"id":"OZyyZQMNiP3fbYBQ6SnF4w","name":"Psychonaut","subtype":"USER"},"type":"CREATE_IDENTITY"},"ledgerTimestamp":1647738965063,"uuid":"awrrq1ugn1bQrxVEuDYvsw","version":"1"}
{"action":{"alias":{"address":"N\u0000sourcecred\u0000discord\u0000MEMBER\u0000user\u0000111882829838684160\u0000","description":"discord/Psychonaut#0216"},"identityId":"OZyyZQMNiP3fbYBQ6SnF4w","type":"ADD_ALIAS"},"ledgerTimestamp":1647738965063,"uuid":"OcyuA7UpguJZRBMhE5ieVQ","version":"1"}
{"action":{"identity":{"address":"N\u0000sourcecred\u0000core\u0000IDENTITY\u0000tMunCWK9xAtw98moOU4VIg\u0000","aliases":[],"id":"tMunCWK9xAtw98moOU4VIg","name":"shid","subtype":"USER"},"type":"CREATE_IDENTITY"},"ledgerTimestamp":1647738965064,"uuid":"2iag1vNcP4PBM35mID1DUQ","version":"1"}
{"action":{"alias":{"address":"N\u0000sourcecred\u0000discord\u0000MEMBER\u0000user\u0000165626765484490753\u0000","description":"discord/shid#2514"},"identityId":"tMunCWK9xAtw98moOU4VIg","type":"ADD_ALIAS"},"ledgerTimestamp":1647738965064,"uuid":"DRDoraEKFAP58lwxyfW38A","version":"1"}
{"action":{"identity":{"address":"N\u0000sourcecred\u0000core\u0000IDENTITY\u0000XsNMWdD7tk922MpJ4BwEng\u0000","aliases":[],"id":"XsNMWdD7tk922MpJ4BwEng","name":"Sina-Iman","subtype":"USER"},"type":"CREATE_IDENTITY"},"ledgerTimestamp":1647738965064,"uuid":"wpyBpAUNgNGkOXxu7wLGmg","version":"1"}
{"action":{"alias":{"address":"N\u0000sourcecred\u0000discord\u0000MEMBER\u0000user\u0000192042086021726208\u0000","description":"discord/Sina-Iman#2897"},"identityId":"XsNMWdD7tk922MpJ4BwEng","type":"ADD_ALIAS"},"ledgerTimestamp":1647738965064,"uuid":"gOYvy4CBO5RXZCQAqSO8EQ","version":"1"}
{"action":{"identity":{"address":"N\u0000sourcecred\u0000core\u0000IDENTITY\u00004Br0yvi8yDkO949GoBqB3g\u0000","aliases":[],"id":"4Br0yvi8yDkO949GoBqB3g","name":"kabat","subtype":"USER"},"type":"CREATE_IDENTITY"},"ledgerTimestamp":1647738965064,"uuid":"Wm4NuO5RCOYqgt5rKyUP2A","version":"1"}
{"action":{"alias":{"address":"N\u0000sourcecred\u0000discord\u0000MEMBER\u0000user\u0000204335630291959809\u0000","description":"discord/kabat#3484"},"identityId":"4Br0yvi8yDkO949GoBqB3g","type":"ADD_ALIAS"},"ledgerTimestamp":1647738965064,"uuid":"VQlncnF42cRbpQoEE4qLrg","version":"1"}
{"action":{"identity":{"address":"N\u0000sourcecred\u0000core\u0000IDENTITY\u0000VvJCN1pOqpxfPuqWJXbV8g\u0000","aliases":[],"id":"VvJCN1pOqpxfPuqWJXbV8g","name":"Braid","subtype":"BOT"},"type":"CREATE_IDENTITY"},"ledgerTimestamp":1647738965064,"uuid":"BGv6FxtdemCObPuDZna3NQ","version":"1"}
{"action":{"alias":{"address":"N\u0000sourcecred\u0000discord\u0000MEMBER\u0000bot\u0000235148962103951360\u0000","description":"discord/Braid#1536"},"identityId":"VvJCN1pOqpxfPuqWJXbV8g","type":"ADD_ALIAS"},"ledgerTimestamp":1647738965064,"uuid":"sOCr2sKp9i4PReZX1Ruysg","version":"1"}
{"action":{"identity":{"address":"N\u0000sourcecred\u0000core\u0000IDENTITY\u0000S2Qgk3a2AGU8g5irOyLwKg\u0000","aliases":[],"id":"S2Qgk3a2AGU8g5irOyLwKg","name":"with-heart","subtype":"USER"},"type":"CREATE_IDENTITY"},"ledgerTimestamp":1647738965065,"uuid":"DyWK7EvnbdHRtbMrvpt7ug","version":"1"}
{"action":{"alias":{"address":"N\u0000sourcecred\u0000discord\u0000MEMBER\u0000user\u0000256500797959831552\u0000","description":"discord/with-heart#0001"},"identityId":"S2Qgk3a2AGU8g5irOyLwKg","type":"ADD_ALIAS"},"ledgerTimestamp":1647738965065,"uuid":"I9YS4t2ONL0dpfZ4uEUZ1g","version":"1"}
{"action":{"identity":{"address":"N\u0000sourcecred\u0000core\u0000IDENTITY\u0000IWbzFymngNE66ueE5cDoCA\u0000","aliases":[],"id":"IWbzFymngNE66ueE5cDoCA","name":"Zira","subtype":"BOT"},"type":"CREATE_IDENTITY"},"ledgerTimestamp":1647738965065,"uuid":"WxBq3nVcon6f5DpC90FvCg","version":"1"}
{"action":{"alias":{"address":"N\u0000sourcecred\u0000discord\u0000MEMBER\u0000bot\u0000275813801792634880\u0000","description":"discord/Zira#9472"},"identityId":"IWbzFymngNE66ueE5cDoCA","type":"ADD_ALIAS"},"ledgerTimestamp":1647738965065,"uuid":"NM6dT2IlmB3t3oHmB3u3IA","version":"1"}
{"action":{"identity":{"address":"N\u0000sourcecred\u0000core\u0000IDENTITY\u0000s660R7RoKiQjCaU1Z18SAA\u0000","aliases":[],"id":"s660R7RoKiQjCaU1Z18SAA","name":"iwa","subtype":"USER"},"type":"CREATE_IDENTITY"},"ledgerTimestamp":1647738965065,"uuid":"om4QJO9j8m7f7r7yxnb1aw","version":"1"}
{"action":{"alias":{"address":"N\u0000sourcecred\u0000discord\u0000MEMBER\u0000user\u0000310798814317379585\u0000","description":"discord/iwa#9749"},"identityId":"s660R7RoKiQjCaU1Z18SAA","type":"ADD_ALIAS"},"ledgerTimestamp":1647738965065,"uuid":"NfGBjBjILGPFDAO2uer9CA","version":"1"}
{"action":{"identity":{"address":"N\u0000sourcecred\u0000core\u0000IDENTITY\u0000CrrHJi2HoVtBCVFGQ9IJDA\u0000","aliases":[],"id":"CrrHJi2HoVtBCVFGQ9IJDA","name":"anush","subtype":"USER"},"type":"CREATE_IDENTITY"},"ledgerTimestamp":1647738965065,"uuid":"XEeEBwZr4hxKUOMURGfk8g","version":"1"}
{"action":{"alias":{"address":"N\u0000sourcecred\u0000discord\u0000MEMBER\u0000user\u0000362218200890474497\u0000","description":"discord/anush#7771"},"identityId":"CrrHJi2HoVtBCVFGQ9IJDA","type":"ADD_ALIAS"},"ledgerTimestamp":1647738965066,"uuid":"kVzcvJ4o569pXr5na49TWg","version":"1"}
{"action":{"identity":{"address":"N\u0000sourcecred\u0000core\u0000IDENTITY\u0000voM9C5RQKIGTrq6H11zNqA\u0000","aliases":[],"id":"voM9C5RQKIGTrq6H11zNqA","name":"willsputra---Gitcoin","subtype":"USER"},"type":"CREATE_IDENTITY"},"ledgerTimestamp":1647738965066,"uuid":"2TelirdYVQMuBcg0zBJzNA","version":"1"}
{"action":{"alias":{"address":"N\u0000sourcecred\u0000discord\u0000MEMBER\u0000user\u0000375850432750157828\u0000","description":"discord/willsputra---Gitcoin#7177"},"identityId":"voM9C5RQKIGTrq6H11zNqA","type":"ADD_ALIAS"},"ledgerTimestamp":1647738965066,"uuid":"lEY0F61Y2cD60qi5dRsnuA","version":"1"}
{"action":{"identity":{"address":"N\u0000sourcecred\u0000core\u0000IDENTITY\u0000E8D6xahdIbXXvVy79FzSaA\u0000","aliases":[],"id":"E8D6xahdIbXXvVy79FzSaA","name":"tobystic","subtype":"USER"},"type":"CREATE_IDENTITY"},"ledgerTimestamp":1647738965066,"uuid":"9f8YKZgq4FzmHr27nKJ0wA","version":"1"}
{"action":{"alias":{"address":"N\u0000sourcecred\u0000discord\u0000MEMBER\u0000user\u0000514565183964839939\u0000","description":"discord/tobystic#5007"},"identityId":"E8D6xahdIbXXvVy79FzSaA","type":"ADD_ALIAS"},"ledgerTimestamp":1647738965066,"uuid":"4YUnfmEFLUgD8d3KPA73aQ","version":"1"}
{"action":{"identity":{"address":"N\u0000sourcecred\u0000core\u0000IDENTITY\u0000Rxejv9ej9ZOBPWGbPBxYNA\u0000","aliases":[],"id":"Rxejv9ej9ZOBPWGbPBxYNA","name":"Chopras---42OPE","subtype":"USER"},"type":"CREATE_IDENTITY"},"ledgerTimestamp":1647738965066,"uuid":"2ZB7MhnqRqwZg03OXSxNnw","version":"1"}
{"action":{"alias":{"address":"N\u0000sourcecred\u0000discord\u0000MEMBER\u0000user\u0000537474612620034069\u0000","description":"discord/Chopras---42OPE#4998"},"identityId":"Rxejv9ej9ZOBPWGbPBxYNA","type":"ADD_ALIAS"},"ledgerTimestamp":1647738965066,"uuid":"gBbVuz0XQKI7g57RzCdQLw","version":"1"}
{"action":{"identity":{"address":"N\u0000sourcecred\u0000core\u0000IDENTITY\u000087bSVTjM8Vs8Hzv5l80nNA\u0000","aliases":[],"id":"87bSVTjM8Vs8Hzv5l80nNA","name":"saulthorin","subtype":"USER"},"type":"CREATE_IDENTITY"},"ledgerTimestamp":1647738965066,"uuid":"fGEqQOZOIdZ7VjwLiM9DfA","version":"1"}
{"action":{"alias":{"address":"N\u0000sourcecred\u0000discord\u0000MEMBER\u0000user\u0000579128660070760469\u0000","description":"discord/saulthorin#7696"},"identityId":"87bSVTjM8Vs8Hzv5l80nNA","type":"ADD_ALIAS"},"ledgerTimestamp":1647738965067,"uuid":"w6JVtr4IDvkFROyd40pmIw","version":"1"}
{"action":{"identity":{"address":"N\u0000sourcecred\u0000core\u0000IDENTITY\u0000Ad0RViPs0XEdbBKRahNAFg\u0000","aliases":[],"id":"Ad0RViPs0XEdbBKRahNAFg","name":"kara","subtype":"USER"},"type":"CREATE_IDENTITY"},"ledgerTimestamp":1647738965068,"uuid":"DlSL9VvHopa9zA1oEcaxQw","version":"1"}
{"action":{"alias":{"address":"N\u0000sourcecred\u0000discord\u0000MEMBER\u0000user\u0000630866784970604564\u0000","description":"discord/kara#0038"},"identityId":"Ad0RViPs0XEdbBKRahNAFg","type":"ADD_ALIAS"},"ledgerTimestamp":1647738965068,"uuid":"29GXpmIOoiVYkYHNwBvk1g","version":"1"}
{"action":{"identity":{"address":"N\u0000sourcecred\u0000core\u0000IDENTITY\u00003E7ac3gZ4hdiZKAkGsrwzA\u0000","aliases":[],"id":"3E7ac3gZ4hdiZKAkGsrwzA","name":"Urek","subtype":"USER"},"type":"CREATE_IDENTITY"},"ledgerTimestamp":1647738965069,"uuid":"8WSNk9Ys5Vy7tof5S5A7Dw","version":"1"}
{"action":{"alias":{"address":"N\u0000sourcecred\u0000discord\u0000MEMBER\u0000user\u0000653878275902275615\u0000","description":"discord/Urek#5014"},"identityId":"3E7ac3gZ4hdiZKAkGsrwzA","type":"ADD_ALIAS"},"ledgerTimestamp":1647738965069,"uuid":"cNja2sLwdq1klh7W8hZE6Q","version":"1"}
{"action":{"identity":{"address":"N\u0000sourcecred\u0000core\u0000IDENTITY\u0000Mg46pMgsKNPbgYlEoCnVaw\u0000","aliases":[],"id":"Mg46pMgsKNPbgYlEoCnVaw","name":"Parikshit","subtype":"USER"},"type":"CREATE_IDENTITY"},"ledgerTimestamp":1647738965069,"uuid":"3ILAob1ty74BpN958rwJhg","version":"1"}
{"action":{"alias":{"address":"N\u0000sourcecred\u0000discord\u0000MEMBER\u0000user\u0000688156591157280768\u0000","description":"discord/Parikshit#5181"},"identityId":"Mg46pMgsKNPbgYlEoCnVaw","type":"ADD_ALIAS"},"ledgerTimestamp":1647738965069,"uuid":"6kd95v5LjCxZFKIeRZQFdg","version":"1"}
{"action":{"identity":{"address":"N\u0000sourcecred\u0000core\u0000IDENTITY\u0000EuQELDkHO9NqiEI4g2MTqw\u0000","aliases":[],"id":"EuQELDkHO9NqiEI4g2MTqw","name":"jayy-leww","subtype":"USER"},"type":"CREATE_IDENTITY"},"ledgerTimestamp":1647738965069,"uuid":"YLwIW3pm6EkZ6mdFjKnsgA","version":"1"}
{"action":{"alias":{"address":"N\u0000sourcecred\u0000discord\u0000MEMBER\u0000user\u0000689941282016985122\u0000","description":"discord/jayy-leww#6202"},"identityId":"EuQELDkHO9NqiEI4g2MTqw","type":"ADD_ALIAS"},"ledgerTimestamp":1647738965069,"uuid":"biDWpVKpZb2pxMeMA6Fp3A","version":"1"}
{"action":{"identity":{"address":"N\u0000sourcecred\u0000core\u0000IDENTITY\u0000LYXQtMsM2ly4V8v6ONDCkw\u0000","aliases":[],"id":"LYXQtMsM2ly4V8v6ONDCkw","name":"Jakub","subtype":"USER"},"type":"CREATE_IDENTITY"},"ledgerTimestamp":1647738965069,"uuid":"KlyuKWxYD7bX7QVmyzF0bQ","version":"1"}
{"action":{"alias":{"address":"N\u0000sourcecred\u0000discord\u0000MEMBER\u0000user\u0000698615884889194587\u0000","description":"discord/Jakub#3317"},"identityId":"LYXQtMsM2ly4V8v6ONDCkw","type":"ADD_ALIAS"},"ledgerTimestamp":1647738965070,"uuid":"Dl2mrb0208GeeJKPVY2Faw","version":"1"}
{"action":{"identity":{"address":"N\u0000sourcecred\u0000core\u0000IDENTITY\u0000nqWh8UqUqCVBiwkx6qfm8g\u0000","aliases":[],"id":"nqWh8UqUqCVBiwkx6qfm8g","name":"Nimi-Vashi","subtype":"USER"},"type":"CREATE_IDENTITY"},"ledgerTimestamp":1647738965070,"uuid":"QvjgUy5Xor5OZBj1h7E6Rw","version":"1"}
{"action":{"alias":{"address":"N\u0000sourcecred\u0000discord\u0000MEMBER\u0000user\u0000699013714317148210\u0000","description":"discord/Nimi-Vashi#8251"},"identityId":"nqWh8UqUqCVBiwkx6qfm8g","type":"ADD_ALIAS"},"ledgerTimestamp":1647738965070,"uuid":"g7wQYMfJpwvNBKj0wixt4A","version":"1"}
{"action":{"identity":{"address":"N\u0000sourcecred\u0000core\u0000IDENTITY\u0000I3KDxUq2j6pL0BNYI4aZxA\u0000","aliases":[],"id":"I3KDxUq2j6pL0BNYI4aZxA","name":"solaria","subtype":"USER"},"type":"CREATE_IDENTITY"},"ledgerTimestamp":1647738965070,"uuid":"wXmCpLq3InhmmcvprZgEWw","version":"1"}
{"action":{"alias":{"address":"N\u0000sourcecred\u0000discord\u0000MEMBER\u0000user\u0000699442991110029362\u0000","description":"discord/solaria#0001"},"identityId":"I3KDxUq2j6pL0BNYI4aZxA","type":"ADD_ALIAS"},"ledgerTimestamp":1647738965070,"uuid":"smmDxqMT3K5K6BuMoPL92A","version":"1"}
{"action":{"identity":{"address":"N\u0000sourcecred\u0000core\u0000IDENTITY\u00008IWa0qQIBesdyt09ZwxoAQ\u0000","aliases":[],"id":"8IWa0qQIBesdyt09ZwxoAQ","name":"ActiveInferenceLab","subtype":"USER"},"type":"CREATE_IDENTITY"},"ledgerTimestamp":1647738965070,"uuid":"lvq7jM53cwlLfwRnOiqRYA","version":"1"}
{"action":{"alias":{"address":"N\u0000sourcecred\u0000discord\u0000MEMBER\u0000user\u0000722593944466096134\u0000","description":"discord/ActiveInferenceLab#3629"},"identityId":"8IWa0qQIBesdyt09ZwxoAQ","type":"ADD_ALIAS"},"ledgerTimestamp":1647738965070,"uuid":"KYKL0r5UjWeL4gFzOg28gQ","version":"1"}
{"action":{"identity":{"address":"N\u0000sourcecred\u0000core\u0000IDENTITY\u0000uwdgSRCpOc5O0gYt0ZSOCA\u0000","aliases":[],"id":"uwdgSRCpOc5O0gYt0ZSOCA","name":"vincenzospaghetti","subtype":"USER"},"type":"CREATE_IDENTITY"},"ledgerTimestamp":1647738965071,"uuid":"TKJJSZUlx2br9M4U6AMi3w","version":"1"}
{"action":{"alias":{"address":"N\u0000sourcecred\u0000discord\u0000MEMBER\u0000user\u0000771410459798274109\u0000","description":"discord/vincenzospaghetti#8265"},"identityId":"uwdgSRCpOc5O0gYt0ZSOCA","type":"ADD_ALIAS"},"ledgerTimestamp":1647738965071,"uuid":"WhMwMJXVrRRG6GgYYyLFAg","version":"1"}
{"action":{"identity":{"address":"N\u0000sourcecred\u0000core\u0000IDENTITY\u0000c2QbkGvIawsaCd36Y4PkeQ\u0000","aliases":[],"id":"c2QbkGvIawsaCd36Y4PkeQ","name":"vintro","subtype":"USER"},"type":"CREATE_IDENTITY"},"ledgerTimestamp":1647738965071,"uuid":"CmW37MDbID42iPeVOUyUvA","version":"1"}
{"action":{"alias":{"address":"N\u0000sourcecred\u0000discord\u0000MEMBER\u0000user\u0000782729216461897798\u0000","description":"discord/vintro#1873"},"identityId":"c2QbkGvIawsaCd36Y4PkeQ","type":"ADD_ALIAS"},"ledgerTimestamp":1647738965071,"uuid":"e8Jw00JJpzBNT9bVkh1p5w","version":"1"}
{"action":{"identity":{"address":"N\u0000sourcecred\u0000core\u0000IDENTITY\u0000nK2ArEa8BKH1bc8ZYa28Nw\u0000","aliases":[],"id":"nK2ArEa8BKH1bc8ZYa28Nw","name":"nicklinck","subtype":"USER"},"type":"CREATE_IDENTITY"},"ledgerTimestamp":1647738965071,"uuid":"pcenjlRhG722CrgTe7NO0A","version":"1"}
{"action":{"alias":{"address":"N\u0000sourcecred\u0000discord\u0000MEMBER\u0000user\u0000783927840638369812\u0000","description":"discord/nicklinck#6691"},"identityId":"nK2ArEa8BKH1bc8ZYa28Nw","type":"ADD_ALIAS"},"ledgerTimestamp":1647738965071,"uuid":"VvmRXKPJbMTXeCvlo6Kn3g","version":"1"}
{"action":{"identity":{"address":"N\u0000sourcecred\u0000core\u0000IDENTITY\u0000GcPqQJgimjH0RvPxnEw2Lw\u0000","aliases":[],"id":"GcPqQJgimjH0RvPxnEw2Lw","name":"nnsk","subtype":"USER"},"type":"CREATE_IDENTITY"},"ledgerTimestamp":1647738965071,"uuid":"BVdfokDaSN0eDvlu4N990Q","version":"1"}
{"action":{"alias":{"address":"N\u0000sourcecred\u0000discord\u0000MEMBER\u0000user\u0000819725310919442472\u0000","description":"discord/nnsk#4182"},"identityId":"GcPqQJgimjH0RvPxnEw2Lw","type":"ADD_ALIAS"},"ledgerTimestamp":1647738965071,"uuid":"W3nNRmGljND6biQXsMg7iQ","version":"1"}
{"action":{"identity":{"address":"N\u0000sourcecred\u0000core\u0000IDENTITY\u0000K3s6DHgvphVv7cngyO0Oqg\u0000","aliases":[],"id":"K3s6DHgvphVv7cngyO0Oqg","name":"DAOlan","subtype":"USER"},"type":"CREATE_IDENTITY"},"ledgerTimestamp":1647738965071,"uuid":"zaUwiPC90evlT4ZZdnW10g","version":"1"}
{"action":{"alias":{"address":"N\u0000sourcecred\u0000discord\u0000MEMBER\u0000user\u0000820450750160830465\u0000","description":"discord/DAOlan#3666"},"identityId":"K3s6DHgvphVv7cngyO0Oqg","type":"ADD_ALIAS"},"ledgerTimestamp":1647738965072,"uuid":"TKTKskxhqGSZEuVhxTjvEQ","version":"1"}
{"action":{"identity":{"address":"N\u0000sourcecred\u0000core\u0000IDENTITY\u00000VQ5xbTxKUKSQ10HpXoAxQ\u0000","aliases":[],"id":"0VQ5xbTxKUKSQ10HpXoAxQ","name":"EA","subtype":"USER"},"type":"CREATE_IDENTITY"},"ledgerTimestamp":1647738965072,"uuid":"gURgiWTlw9dDPo8jjNv4Qg","version":"1"}
{"action":{"alias":{"address":"N\u0000sourcecred\u0000discord\u0000MEMBER\u0000user\u0000825462846410326098\u0000","description":"discord/EA#4220"},"identityId":"0VQ5xbTxKUKSQ10HpXoAxQ","type":"ADD_ALIAS"},"ledgerTimestamp":1647738965072,"uuid":"d4WEO0p0qWu6GOiZ0Y3MDw","version":"1"}
{"action":{"identity":{"address":"N\u0000sourcecred\u0000core\u0000IDENTITY\u0000YdOoKbrZi0kJhxVtLQBUng\u0000","aliases":[],"id":"YdOoKbrZi0kJhxVtLQBUng","name":"Radiant-Ad-9137","subtype":"USER"},"type":"CREATE_IDENTITY"},"ledgerTimestamp":1647738965072,"uuid":"UznKtYv8Wf0ET4iwSzmhxg","version":"1"}
{"action":{"alias":{"address":"N\u0000sourcecred\u0000discord\u0000MEMBER\u0000user\u0000825766730361208923\u0000","description":"discord/Radiant-Ad-9137#6939"},"identityId":"YdOoKbrZi0kJhxVtLQBUng","type":"ADD_ALIAS"},"ledgerTimestamp":1647738965072,"uuid":"y8FV6qvHzGYoS8SQ2nRRdQ","version":"1"}
{"action":{"identity":{"address":"N\u0000sourcecred\u0000core\u0000IDENTITY\u0000HM6Y02eYzJ0iG7aLcWzhVw\u0000","aliases":[],"id":"HM6Y02eYzJ0iG7aLcWzhVw","name":"an-libertine","subtype":"USER"},"type":"CREATE_IDENTITY"},"ledgerTimestamp":1647738965072,"uuid":"3zZEy8H534hDE1SOTkoRZg","version":"1"}
{"action":{"alias":{"address":"N\u0000sourcecred\u0000discord\u0000MEMBER\u0000user\u0000859519093152415754\u0000","description":"discord/an-libertine#3342"},"identityId":"HM6Y02eYzJ0iG7aLcWzhVw","type":"ADD_ALIAS"},"ledgerTimestamp":1647738965073,"uuid":"QeFdYPQRvTGiNkw0LiKGDA","version":"1"}
{"action":{"identity":{"address":"N\u0000sourcecred\u0000core\u0000IDENTITY\u0000a6OQFDhYMp1cewb2LXWu9g\u0000","aliases":[],"id":"a6OQFDhYMp1cewb2LXWu9g","name":"sidcode","subtype":"USER"},"type":"CREATE_IDENTITY"},"ledgerTimestamp":1647738965073,"uuid":"wt75zktdXbeixgAg4k42cg","version":"1"}
{"action":{"alias":{"address":"N\u0000sourcecred\u0000discord\u0000MEMBER\u0000user\u0000861513367700111360\u0000","description":"discord/sidcode#1729"},"identityId":"a6OQFDhYMp1cewb2LXWu9g","type":"ADD_ALIAS"},"ledgerTimestamp":1647738965073,"uuid":"EXo6xMkkqP8nmBCnO9ZOYw","version":"1"}
{"action":{"identity":{"address":"N\u0000sourcecred\u0000core\u0000IDENTITY\u00005gQ88sMqrvELIxFJ5qXpeQ\u0000","aliases":[],"id":"5gQ88sMqrvELIxFJ5qXpeQ","name":"oak","subtype":"USER"},"type":"CREATE_IDENTITY"},"ledgerTimestamp":1647738965073,"uuid":"JMRArI9paBAk17PYT0zvyA","version":"1"}
{"action":{"alias":{"address":"N\u0000sourcecred\u0000discord\u0000MEMBER\u0000user\u0000903754357915418704\u0000","description":"discord/oak#0972"},"identityId":"5gQ88sMqrvELIxFJ5qXpeQ","type":"ADD_ALIAS"},"ledgerTimestamp":1647738965073,"uuid":"anrWeyYDu8v4TDB4Tn4leg","version":"1"}
{"action":{"identity":{"address":"N\u0000sourcecred\u0000core\u0000IDENTITY\u0000DoSxDT8279fOE3x5Yelx7Q\u0000","aliases":[],"id":"DoSxDT8279fOE3x5Yelx7Q","name":"carlaost","subtype":"USER"},"type":"CREATE_IDENTITY"},"ledgerTimestamp":1647738965073,"uuid":"L4AF4r46vcKMbIgcJ1IByw","version":"1"}
{"action":{"alias":{"address":"N\u0000sourcecred\u0000discord\u0000MEMBER\u0000user\u0000910940211754700882\u0000","description":"discord/carlaost#5298"},"identityId":"DoSxDT8279fOE3x5Yelx7Q","type":"ADD_ALIAS"},"ledgerTimestamp":1647738965073,"uuid":"S1wY9ZW7ZDVpGgECGXqQ1Q","version":"1"}
{"action":{"identity":{"address":"N\u0000sourcecred\u0000core\u0000IDENTITY\u0000FJPiy53sWXIQavrWB3yM5w\u0000","aliases":[],"id":"FJPiy53sWXIQavrWB3yM5w","name":"laura314","subtype":"USER"},"type":"CREATE_IDENTITY"},"ledgerTimestamp":1647738965073,"uuid":"s2kB9WhwDkw5nrpf6PgdLw","version":"1"}
{"action":{"alias":{"address":"N\u0000sourcecred\u0000discord\u0000MEMBER\u0000user\u0000921239888039391313\u0000","description":"discord/laura314#2123"},"identityId":"FJPiy53sWXIQavrWB3yM5w","type":"ADD_ALIAS"},"ledgerTimestamp":1647738965073,"uuid":"tKoHy6KqNOGTgNaMsXbfLQ","version":"1"}
