{"action":{"identity":{"address":"N\u0000sourcecred\u0000core\u0000IDENTITY\u0000qSqDm0yiViDHwDWhP6o7HA\u0000","aliases":[],"id":"qSqDm0yiViDHwDWhP6o7HA","name":"Ekkeharta","subtype":"USER"},"type":"CREATE_IDENTITY"},"ledgerTimestamp":1642096891703,"uuid":"uJD1lo61GEZoV8FwydqWfQ","version":"1"}
{"action":{"alias":{"address":"N\u0000sourcecred\u0000discord\u0000MEMBER\u0000user\u0000131942579985055744\u0000","description":"discord/Ekkeharta#3447"},"identityId":"qSqDm0yiViDHwDWhP6o7HA","type":"ADD_ALIAS"},"ledgerTimestamp":1642096891703,"uuid":"FBeCkTV7qQyopYXrcJVobQ","version":"1"}
{"action":{"identity":{"address":"N\u0000sourcecred\u0000core\u0000IDENTITY\u0000euW99YR9WlKvJi6Q1DVxQQ\u0000","aliases":[],"id":"euW99YR9WlKvJi6Q1DVxQQ","name":"Leyoric","subtype":"USER"},"type":"CREATE_IDENTITY"},"ledgerTimestamp":1642096891704,"uuid":"bZpR2OIMNArAkWBWqiGdqQ","version":"1"}
{"action":{"alias":{"address":"N\u0000sourcecred\u0000discord\u0000MEMBER\u0000user\u0000134423116959973378\u0000","description":"discord/Leyoric#9095"},"identityId":"euW99YR9WlKvJi6Q1DVxQQ","type":"ADD_ALIAS"},"ledgerTimestamp":1642096891704,"uuid":"ymZ1OOnS8pdjbAx4m9F82A","version":"1"}
{"action":{"identity":{"address":"N\u0000sourcecred\u0000core\u0000IDENTITY\u0000oNlPIDpeEMlkwL8UYtBr1g\u0000","aliases":[],"id":"oNlPIDpeEMlkwL8UYtBr1g","name":"HomicidalChicken","subtype":"USER"},"type":"CREATE_IDENTITY"},"ledgerTimestamp":1642096891704,"uuid":"QEyE09S8YoPmXd7GPvRwOg","version":"1"}
{"action":{"alias":{"address":"N\u0000sourcecred\u0000discord\u0000MEMBER\u0000user\u0000221288305222877185\u0000","description":"discord/HomicidalChicken#8326"},"identityId":"oNlPIDpeEMlkwL8UYtBr1g","type":"ADD_ALIAS"},"ledgerTimestamp":1642096891705,"uuid":"HJzj6kekvkIm5b0VQsveMQ","version":"1"}
{"action":{"identity":{"address":"N\u0000sourcecred\u0000core\u0000IDENTITY\u0000qcXYSMhDbKsRbWOq9E1lNA\u0000","aliases":[],"id":"qcXYSMhDbKsRbWOq9E1lNA","name":"Dank-Mona","subtype":"USER"},"type":"CREATE_IDENTITY"},"ledgerTimestamp":1642096891705,"uuid":"WurNk0FdbjLR8Nf8eI1j5g","version":"1"}
{"action":{"alias":{"address":"N\u0000sourcecred\u0000discord\u0000MEMBER\u0000user\u0000225311920754786304\u0000","description":"discord/Dank-Mona#4426"},"identityId":"qcXYSMhDbKsRbWOq9E1lNA","type":"ADD_ALIAS"},"ledgerTimestamp":1642096891705,"uuid":"x9MyTqCGei6jll0XztDDIA","version":"1"}
{"action":{"identity":{"address":"N\u0000sourcecred\u0000core\u0000IDENTITY\u0000AJIk0MDdXDflP7e7Jz11Eg\u0000","aliases":[],"id":"AJIk0MDdXDflP7e7Jz11Eg","name":"ufkhan97","subtype":"USER"},"type":"CREATE_IDENTITY"},"ledgerTimestamp":1642096891705,"uuid":"r1QcQo6ikdvuOxc6DdFwDg","version":"1"}
{"action":{"alias":{"address":"N\u0000sourcecred\u0000discord\u0000MEMBER\u0000user\u0000259178972301099008\u0000","description":"discord/ufkhan97#4345"},"identityId":"AJIk0MDdXDflP7e7Jz11Eg","type":"ADD_ALIAS"},"ledgerTimestamp":1642096891706,"uuid":"Nzj1Nh6CrWxrkcyHKE1Afw","version":"1"}
{"action":{"identity":{"address":"N\u0000sourcecred\u0000core\u0000IDENTITY\u0000abbugaXtn28tEHNXqL7LMg\u0000","aliases":[],"id":"abbugaXtn28tEHNXqL7LMg","name":"-BrianMillsJr","subtype":"USER"},"type":"CREATE_IDENTITY"},"ledgerTimestamp":1642096891706,"uuid":"R7OtXSaYVoC4BKrLqd405w","version":"1"}
{"action":{"alias":{"address":"N\u0000sourcecred\u0000discord\u0000MEMBER\u0000user\u0000325811370195156994\u0000","description":"discord/-BrianMillsJr#5987"},"identityId":"abbugaXtn28tEHNXqL7LMg","type":"ADD_ALIAS"},"ledgerTimestamp":1642096891706,"uuid":"2R3nrwEgdXw8yxJ8pvDNFg","version":"1"}
{"action":{"identity":{"address":"N\u0000sourcecred\u0000core\u0000IDENTITY\u0000emc7HZr0xE74N4L7ZEYLDQ\u0000","aliases":[],"id":"emc7HZr0xE74N4L7ZEYLDQ","name":"crossoveranx","subtype":"USER"},"type":"CREATE_IDENTITY"},"ledgerTimestamp":1642096891706,"uuid":"4BcnAZBapJoyq3sM79nyJA","version":"1"}
{"action":{"alias":{"address":"N\u0000sourcecred\u0000discord\u0000MEMBER\u0000user\u0000379030669201768448\u0000","description":"discord/crossoveranx#1832"},"identityId":"emc7HZr0xE74N4L7ZEYLDQ","type":"ADD_ALIAS"},"ledgerTimestamp":1642096891706,"uuid":"MiLhXmIbrX3fERBsdaWLEw","version":"1"}
{"action":{"identity":{"address":"N\u0000sourcecred\u0000core\u0000IDENTITY\u0000b3RQ7kRgN57eWx70SpO4YA\u0000","aliases":[],"id":"b3RQ7kRgN57eWx70SpO4YA","name":"Keturin","subtype":"USER"},"type":"CREATE_IDENTITY"},"ledgerTimestamp":1642096891706,"uuid":"ok9k966R6BMvbz93RyLDDw","version":"1"}
{"action":{"alias":{"address":"N\u0000sourcecred\u0000discord\u0000MEMBER\u0000user\u0000455016695174529025\u0000","description":"discord/Keturin#6669"},"identityId":"b3RQ7kRgN57eWx70SpO4YA","type":"ADD_ALIAS"},"ledgerTimestamp":1642096891706,"uuid":"OmzYNhz0aM0rYoq0ptXDpQ","version":"1"}
{"action":{"identity":{"address":"N\u0000sourcecred\u0000core\u0000IDENTITY\u0000ZLOW51V8UnpfQDJFKByzlg\u0000","aliases":[],"id":"ZLOW51V8UnpfQDJFKByzlg","name":"llllvvuu","subtype":"USER"},"type":"CREATE_IDENTITY"},"ledgerTimestamp":1642096891707,"uuid":"Bv7qI2gX5qBTexhGl7w3JA","version":"1"}
{"action":{"alias":{"address":"N\u0000sourcecred\u0000discord\u0000MEMBER\u0000user\u0000522402421566078978\u0000","description":"discord/llllvvuu#1782"},"identityId":"ZLOW51V8UnpfQDJFKByzlg","type":"ADD_ALIAS"},"ledgerTimestamp":1642096891707,"uuid":"Wh5FKKuZY14zVZwopdYr6g","version":"1"}
{"action":{"identity":{"address":"N\u0000sourcecred\u0000core\u0000IDENTITY\u0000nmAHnsxJ4nXbWlf9g8U41A\u0000","aliases":[],"id":"nmAHnsxJ4nXbWlf9g8U41A","name":"Mike-Elias","subtype":"USER"},"type":"CREATE_IDENTITY"},"ledgerTimestamp":1642096891707,"uuid":"BvasLlKdLXMGy7wgM7zH9A","version":"1"}
{"action":{"alias":{"address":"N\u0000sourcecred\u0000discord\u0000MEMBER\u0000user\u0000626178021120016395\u0000","description":"discord/Mike-Elias#4724"},"identityId":"nmAHnsxJ4nXbWlf9g8U41A","type":"ADD_ALIAS"},"ledgerTimestamp":1642096891707,"uuid":"Mm1vxlmoeokCdwgbQwb37w","version":"1"}
{"action":{"identity":{"address":"N\u0000sourcecred\u0000core\u0000IDENTITY\u000039N9YIQ3WwDTGmk2w2uLBg\u0000","aliases":[],"id":"39N9YIQ3WwDTGmk2w2uLBg","name":"Shamburgularara---XXI","subtype":"USER"},"type":"CREATE_IDENTITY"},"ledgerTimestamp":1642096891707,"uuid":"BPO41AdIjulIRFNVlQnMow","version":"1"}
{"action":{"alias":{"address":"N\u0000sourcecred\u0000discord\u0000MEMBER\u0000user\u0000718139779509911623\u0000","description":"discord/Shamburgularara---XXI#7217"},"identityId":"39N9YIQ3WwDTGmk2w2uLBg","type":"ADD_ALIAS"},"ledgerTimestamp":1642096891707,"uuid":"9DP885uQegZ23maBj4idwA","version":"1"}
{"action":{"identity":{"address":"N\u0000sourcecred\u0000core\u0000IDENTITY\u0000zH9ndQ4KkmMQmCAYDYUjwQ\u0000","aliases":[],"id":"zH9ndQ4KkmMQmCAYDYUjwQ","name":"darren","subtype":"USER"},"type":"CREATE_IDENTITY"},"ledgerTimestamp":1642096891707,"uuid":"899Sx46Swn4tL5ulrzaqzA","version":"1"}
{"action":{"alias":{"address":"N\u0000sourcecred\u0000discord\u0000MEMBER\u0000user\u0000852800209611653120\u0000","description":"discord/darren#1994"},"identityId":"zH9ndQ4KkmMQmCAYDYUjwQ","type":"ADD_ALIAS"},"ledgerTimestamp":1642096891707,"uuid":"Eph3h6HNwlK8wQntXBqh0Q","version":"1"}
{"action":{"identity":{"address":"N\u0000sourcecred\u0000core\u0000IDENTITY\u00004xAvDI2FlIDrq5yNYyggQw\u0000","aliases":[],"id":"4xAvDI2FlIDrq5yNYyggQw","name":"tone123456789","subtype":"USER"},"type":"CREATE_IDENTITY"},"ledgerTimestamp":1642096891708,"uuid":"KLm6QupP7AtRPVrImxUK7w","version":"1"}
{"action":{"alias":{"address":"N\u0000sourcecred\u0000discord\u0000MEMBER\u0000user\u0000902331794387533864\u0000","description":"discord/tone123456789#6303"},"identityId":"4xAvDI2FlIDrq5yNYyggQw","type":"ADD_ALIAS"},"ledgerTimestamp":1642096891708,"uuid":"d8VeFXAsZcLjH0zb6uyU3g","version":"1"}
{"action":{"identity":{"address":"N\u0000sourcecred\u0000core\u0000IDENTITY\u0000Pe6A0Kl0e6xwjb29MQ7rig\u0000","aliases":[],"id":"Pe6A0Kl0e6xwjb29MQ7rig","name":"sam76021","subtype":"USER"},"type":"CREATE_IDENTITY"},"ledgerTimestamp":1642096891708,"uuid":"bsE1W3qAdXWLIzi6jHggWw","version":"1"}
{"action":{"alias":{"address":"N\u0000sourcecred\u0000discord\u0000MEMBER\u0000user\u0000905595868768501831\u0000","description":"discord/sam76021#2389"},"identityId":"Pe6A0Kl0e6xwjb29MQ7rig","type":"ADD_ALIAS"},"ledgerTimestamp":1642096891708,"uuid":"FjqaLu4yKIev988ecaCO2w","version":"1"}
{"action":{"identity":{"address":"N\u0000sourcecred\u0000core\u0000IDENTITY\u0000W3w8X7cGwvt7fp5XrVskag\u0000","aliases":[],"id":"W3w8X7cGwvt7fp5XrVskag","name":"versusmikehistory","subtype":"USER"},"type":"CREATE_IDENTITY"},"ledgerTimestamp":1642096891708,"uuid":"DIQDRO7gQIK8U1xWJ7HPrA","version":"1"}
{"action":{"alias":{"address":"N\u0000sourcecred\u0000discord\u0000MEMBER\u0000user\u0000921920605400469554\u0000","description":"discord/versusmikehistory#0363"},"identityId":"W3w8X7cGwvt7fp5XrVskag","type":"ADD_ALIAS"},"ledgerTimestamp":1642096891708,"uuid":"DRtDai1GF3H8r4hlEbOUQw","version":"1"}
{"action":{"identity":{"address":"N\u0000sourcecred\u0000core\u0000IDENTITY\u0000qkGQO5ba65R7h0J1SxK2fA\u0000","aliases":[],"id":"qkGQO5ba65R7h0J1SxK2fA","name":"SourceCred-Braid-Bot","subtype":"BOT"},"type":"CREATE_IDENTITY"},"ledgerTimestamp":1642096891708,"uuid":"WBjxPZLl23rJmBAJQKMwHA","version":"1"}
{"action":{"alias":{"address":"N\u0000sourcecred\u0000discord\u0000MEMBER\u0000bot\u0000930561335492767744\u0000","description":"discord/SourceCred-Braid-Bot#3393"},"identityId":"qkGQO5ba65R7h0J1SxK2fA","type":"ADD_ALIAS"},"ledgerTimestamp":1642096891708,"uuid":"YoNbUrCEGzK1UVS8Zg7Zsg","version":"1"}
{"action":{"identity":{"address":"N\u0000sourcecred\u0000core\u0000IDENTITY\u0000rp9eJcE639XgmVT1V6sj7g\u0000","aliases":[],"id":"rp9eJcE639XgmVT1V6sj7g","name":"decentralion","subtype":"USER"},"type":"CREATE_IDENTITY"},"ledgerTimestamp":1642096892188,"uuid":"soGUO3M78XZ8z56A77HGIw","version":"1"}
{"action":{"alias":{"address":"N\u0000sourcecred\u0000github\u0000USERLIKE\u0000USER\u0000decentralion\u0000","description":"github/[@decentralion](https://github.com/decentralion)"},"identityId":"rp9eJcE639XgmVT1V6sj7g","type":"ADD_ALIAS"},"ledgerTimestamp":1642096892188,"uuid":"OkaBJYG6ioRi4idyZfL9OA","version":"1"}
{"action":{"identity":{"address":"N\u0000sourcecred\u0000core\u0000IDENTITY\u0000ZIGr9w3s1sxLCpSphMqqlg\u0000","aliases":[],"id":"ZIGr9w3s1sxLCpSphMqqlg","name":"credbot","subtype":"BOT"},"type":"CREATE_IDENTITY"},"ledgerTimestamp":1642096892188,"uuid":"zbupbPndX205W194t1KA2Q","version":"1"}
{"action":{"alias":{"address":"N\u0000sourcecred\u0000github\u0000USERLIKE\u0000BOT\u0000credbot\u0000","description":"github/[@credbot](https://github.com/credbot)"},"identityId":"ZIGr9w3s1sxLCpSphMqqlg","type":"ADD_ALIAS"},"ledgerTimestamp":1642096892188,"uuid":"RXQu0WwO5PIj9Ij2SlBTYg","version":"1"}
{"action":{"identity":{"address":"N\u0000sourcecred\u0000core\u0000IDENTITY\u0000Vt2674qUGfxL5ZezDTVrzA\u0000","aliases":[],"id":"Vt2674qUGfxL5ZezDTVrzA","name":"wchargin","subtype":"USER"},"type":"CREATE_IDENTITY"},"ledgerTimestamp":1642096892189,"uuid":"Cx6ieppR8o8WWJeXcvpKyg","version":"1"}
{"action":{"alias":{"address":"N\u0000sourcecred\u0000github\u0000USERLIKE\u0000USER\u0000wchargin\u0000","description":"github/[@wchargin](https://github.com/wchargin)"},"identityId":"Vt2674qUGfxL5ZezDTVrzA","type":"ADD_ALIAS"},"ledgerTimestamp":1642096892189,"uuid":"9DXbBeEMJ4DHmWYSKdJaAQ","version":"1"}
{"action":{"identity":{"address":"N\u0000sourcecred\u0000core\u0000IDENTITY\u0000ta1ouAqKPYSnb0BK3aoFxA\u0000","aliases":[],"id":"ta1ouAqKPYSnb0BK3aoFxA","name":"SourceCred","subtype":"PROJECT"},"type":"CREATE_IDENTITY"},"ledgerTimestamp":1642096892261,"uuid":"RRl4wmMEP0pj42aVuaVNKA","version":"1"}
{"action":{"identityId":"ta1ouAqKPYSnb0BK3aoFxA","type":"TOGGLE_ACTIVATION"},"ledgerTimestamp":1642096892261,"uuid":"g67m66hMCpA90jqlWx7YHA","version":"1"}
{"action":{"identity":{"address":"N\u0000sourcecred\u0000core\u0000IDENTITY\u0000gQPqEOdbgoFRSxRFQpfyMA\u0000","aliases":[],"id":"gQPqEOdbgoFRSxRFQpfyMA","name":"yung-calibri","subtype":"USER"},"type":"CREATE_IDENTITY"},"ledgerTimestamp":1649986126699,"uuid":"sktJ1ddoqG2X0VnZsdYKaQ","version":"1"}
{"action":{"alias":{"address":"N\u0000sourcecred\u0000discord\u0000MEMBER\u0000user\u0000132055527504084992\u0000","description":"discord/yung-calibri#0225"},"identityId":"gQPqEOdbgoFRSxRFQpfyMA","type":"ADD_ALIAS"},"ledgerTimestamp":1649986126699,"uuid":"KIRXvc9ACmYNd7jsDUxeqA","version":"1"}
{"action":{"identity":{"address":"N\u0000sourcecred\u0000core\u0000IDENTITY\u0000nUrA3NXHV50wqoL7kpZ7Xg\u0000","aliases":[],"id":"nUrA3NXHV50wqoL7kpZ7Xg","name":"LaRiccia","subtype":"USER"},"type":"CREATE_IDENTITY"},"ledgerTimestamp":1649986126699,"uuid":"1r0IvqCOPW6XCzmqoPn4hQ","version":"1"}
{"action":{"alias":{"address":"N\u0000sourcecred\u0000discord\u0000MEMBER\u0000user\u0000193041322150461440\u0000","description":"discord/LaRiccia#6314"},"identityId":"nUrA3NXHV50wqoL7kpZ7Xg","type":"ADD_ALIAS"},"ledgerTimestamp":1649986126700,"uuid":"m5l8EESlH5dbyCW5kX8zpg","version":"1"}
{"action":{"identity":{"address":"N\u0000sourcecred\u0000core\u0000IDENTITY\u00005aNkQ3jv3uJqKrVIWBcKtg\u0000","aliases":[],"id":"5aNkQ3jv3uJqKrVIWBcKtg","name":"rabage","subtype":"USER"},"type":"CREATE_IDENTITY"},"ledgerTimestamp":1649986126701,"uuid":"j7KLiQjaWtQZ03Mq5sLQfQ","version":"1"}
{"action":{"alias":{"address":"N\u0000sourcecred\u0000discord\u0000MEMBER\u0000user\u0000220712729172770816\u0000","description":"discord/rabage#0897"},"identityId":"5aNkQ3jv3uJqKrVIWBcKtg","type":"ADD_ALIAS"},"ledgerTimestamp":1649986126701,"uuid":"ORBNZ36AgaE8jwDPw1NrBA","version":"1"}
{"action":{"identity":{"address":"N\u0000sourcecred\u0000core\u0000IDENTITY\u0000RryREGfKrpC7j8bXkV021Q\u0000","aliases":[],"id":"RryREGfKrpC7j8bXkV021Q","name":"chicken-sharoofi","subtype":"USER"},"type":"CREATE_IDENTITY"},"ledgerTimestamp":1649986126701,"uuid":"l4rfRCQBL0IkNbvgJknhkA","version":"1"}
{"action":{"alias":{"address":"N\u0000sourcecred\u0000discord\u0000MEMBER\u0000user\u0000341767134495375363\u0000","description":"discord/chicken-sharoofi#4385"},"identityId":"RryREGfKrpC7j8bXkV021Q","type":"ADD_ALIAS"},"ledgerTimestamp":1649986126701,"uuid":"Mt3Rsd5I1qYWuAPvvBWTng","version":"1"}
{"action":{"identity":{"address":"N\u0000sourcecred\u0000core\u0000IDENTITY\u0000h3PDzzrkV0T9JuOVqBjDWg\u0000","aliases":[],"id":"h3PDzzrkV0T9JuOVqBjDWg","name":"MantisClone","subtype":"USER"},"type":"CREATE_IDENTITY"},"ledgerTimestamp":1649986126702,"uuid":"53S9wh3f0bjz2dGbUJVCpg","version":"1"}
{"action":{"alias":{"address":"N\u0000sourcecred\u0000discord\u0000MEMBER\u0000user\u0000369700858742571008\u0000","description":"discord/MantisClone#2619"},"identityId":"h3PDzzrkV0T9JuOVqBjDWg","type":"ADD_ALIAS"},"ledgerTimestamp":1649986126702,"uuid":"G0OdR42XjA4wWAaXY5T7jw","version":"1"}
{"action":{"identity":{"address":"N\u0000sourcecred\u0000core\u0000IDENTITY\u00003IddAtXD4i6ZVl4JrQdTEw\u0000","aliases":[],"id":"3IddAtXD4i6ZVl4JrQdTEw","name":"heintess","subtype":"USER"},"type":"CREATE_IDENTITY"},"ledgerTimestamp":1649986126702,"uuid":"cJq1E7Xpx7JMLagFmdF0qA","version":"1"}
{"action":{"alias":{"address":"N\u0000sourcecred\u0000discord\u0000MEMBER\u0000user\u0000398278221319372801\u0000","description":"discord/heintess#7769"},"identityId":"3IddAtXD4i6ZVl4JrQdTEw","type":"ADD_ALIAS"},"ledgerTimestamp":1649986126702,"uuid":"mogXSwD2CqWbcE593rLRmw","version":"1"}
{"action":{"identity":{"address":"N\u0000sourcecred\u0000core\u0000IDENTITY\u0000f6aMOTnYNtnyvQO10TvDuw\u0000","aliases":[],"id":"f6aMOTnYNtnyvQO10TvDuw","name":"JB87","subtype":"USER"},"type":"CREATE_IDENTITY"},"ledgerTimestamp":1649986126703,"uuid":"QxaI9koqg88uOAAdKzR5mg","version":"1"}
{"action":{"alias":{"address":"N\u0000sourcecred\u0000discord\u0000MEMBER\u0000user\u0000400321205724512267\u0000","description":"discord/JB87#8474"},"identityId":"f6aMOTnYNtnyvQO10TvDuw","type":"ADD_ALIAS"},"ledgerTimestamp":1649986126703,"uuid":"AgZwRqw7qu4iMSVKzS9JXw","version":"1"}
{"action":{"identity":{"address":"N\u0000sourcecred\u0000core\u0000IDENTITY\u0000BEUeHrZ2GX0FGCxwpYXgUA\u0000","aliases":[],"id":"BEUeHrZ2GX0FGCxwpYXgUA","name":"rush0","subtype":"USER"},"type":"CREATE_IDENTITY"},"ledgerTimestamp":1649986126703,"uuid":"k1pXMLu4waOhy5zqkaOmkA","version":"1"}
{"action":{"alias":{"address":"N\u0000sourcecred\u0000discord\u0000MEMBER\u0000user\u0000409745838441758721\u0000","description":"discord/rush0#5067"},"identityId":"BEUeHrZ2GX0FGCxwpYXgUA","type":"ADD_ALIAS"},"ledgerTimestamp":1649986126704,"uuid":"QHeuWVAKQSXbKPnDbAQveA","version":"1"}
{"action":{"identity":{"address":"N\u0000sourcecred\u0000core\u0000IDENTITY\u0000EeLlgApgpn7dW82avNs6vw\u0000","aliases":[],"id":"EeLlgApgpn7dW82avNs6vw","name":"bestape","subtype":"USER"},"type":"CREATE_IDENTITY"},"ledgerTimestamp":1649986126705,"uuid":"1dnZ3VwJyeyX1BAuLbePSg","version":"1"}
{"action":{"alias":{"address":"N\u0000sourcecred\u0000discord\u0000MEMBER\u0000user\u0000476451739516534799\u0000","description":"discord/bestape#3069"},"identityId":"EeLlgApgpn7dW82avNs6vw","type":"ADD_ALIAS"},"ledgerTimestamp":1649986126705,"uuid":"T6ZNuBDVBpglvTxUZz9PUw","version":"1"}
{"action":{"identity":{"address":"N\u0000sourcecred\u0000core\u0000IDENTITY\u00002wWn1g7KI9kGPzNLPTG83w\u0000","aliases":[],"id":"2wWn1g7KI9kGPzNLPTG83w","name":"GuavaGabriel","subtype":"USER"},"type":"CREATE_IDENTITY"},"ledgerTimestamp":1649986126705,"uuid":"Oi33O8x1gRmeynynGO2oHQ","version":"1"}
{"action":{"alias":{"address":"N\u0000sourcecred\u0000discord\u0000MEMBER\u0000user\u0000579305699281207307\u0000","description":"discord/GuavaGabriel#6530"},"identityId":"2wWn1g7KI9kGPzNLPTG83w","type":"ADD_ALIAS"},"ledgerTimestamp":1649986126706,"uuid":"DbfW2HOk23eBeM6d0umrew","version":"1"}
{"action":{"identity":{"address":"N\u0000sourcecred\u0000core\u0000IDENTITY\u0000rbJDgMdMzDbaRFDPQVUliA\u0000","aliases":[],"id":"rbJDgMdMzDbaRFDPQVUliA","name":"eugene---SCRF","subtype":"USER"},"type":"CREATE_IDENTITY"},"ledgerTimestamp":1649986126706,"uuid":"yqOExve5irEIj4a0OZORiQ","version":"1"}
{"action":{"alias":{"address":"N\u0000sourcecred\u0000discord\u0000MEMBER\u0000user\u0000620452002425470977\u0000","description":"discord/eugene---SCRF#1706"},"identityId":"rbJDgMdMzDbaRFDPQVUliA","type":"ADD_ALIAS"},"ledgerTimestamp":1649986126706,"uuid":"CEQsD2i7AOel7wMPFbcgbA","version":"1"}
{"action":{"identity":{"address":"N\u0000sourcecred\u0000core\u0000IDENTITY\u000029IqmFXOzU4MCBd7XiAFNw\u0000","aliases":[],"id":"29IqmFXOzU4MCBd7XiAFNw","name":"hebbianloop","subtype":"USER"},"type":"CREATE_IDENTITY"},"ledgerTimestamp":1649986126706,"uuid":"8LjG5K2sQo08VGzRu7AnCw","version":"1"}
{"action":{"alias":{"address":"N\u0000sourcecred\u0000discord\u0000MEMBER\u0000user\u0000646837640980856862\u0000","description":"discord/hebbianloop#5169"},"identityId":"29IqmFXOzU4MCBd7XiAFNw","type":"ADD_ALIAS"},"ledgerTimestamp":1649986126706,"uuid":"J0uZKauRXTDGKumpyAhWFA","version":"1"}
{"action":{"identity":{"address":"N\u0000sourcecred\u0000core\u0000IDENTITY\u00007kFgWoXOTYLkq17Hjaj2lA\u0000","aliases":[],"id":"7kFgWoXOTYLkq17Hjaj2lA","name":"Craig","subtype":"USER"},"type":"CREATE_IDENTITY"},"ledgerTimestamp":1649986126706,"uuid":"3KYHogJV5HlYSvUVkoYKuQ","version":"1"}
{"action":{"alias":{"address":"N\u0000sourcecred\u0000discord\u0000MEMBER\u0000user\u0000655144629481635841\u0000","description":"discord/Craig#0979"},"identityId":"7kFgWoXOTYLkq17Hjaj2lA","type":"ADD_ALIAS"},"ledgerTimestamp":1649986126707,"uuid":"OImjjSzngpZZCYew9Mc0Ag","version":"1"}
{"action":{"identity":{"address":"N\u0000sourcecred\u0000core\u0000IDENTITY\u0000idGNN7HObh7QpHXvwQd7yQ\u0000","aliases":[],"id":"idGNN7HObh7QpHXvwQd7yQ","name":"Xena","subtype":"USER"},"type":"CREATE_IDENTITY"},"ledgerTimestamp":1649986126707,"uuid":"Plu9u5LNcvmQdEBrk5yXWA","version":"1"}
{"action":{"alias":{"address":"N\u0000sourcecred\u0000discord\u0000MEMBER\u0000user\u0000690682149195481268\u0000","description":"discord/Xena#1289"},"identityId":"idGNN7HObh7QpHXvwQd7yQ","type":"ADD_ALIAS"},"ledgerTimestamp":1649986126707,"uuid":"Xzx8hKFAC6pykR3G9WdIBA","version":"1"}
{"action":{"identity":{"address":"N\u0000sourcecred\u0000core\u0000IDENTITY\u0000YDbJw40NcoQp6Gx1lGdZOw\u0000","aliases":[],"id":"YDbJw40NcoQp6Gx1lGdZOw","name":"dvwz","subtype":"USER"},"type":"CREATE_IDENTITY"},"ledgerTimestamp":1649986126707,"uuid":"z3IMiZv3bh5XTkXJDlUOzg","version":"1"}
{"action":{"alias":{"address":"N\u0000sourcecred\u0000discord\u0000MEMBER\u0000user\u0000707869170657919027\u0000","description":"discord/dvwz#7836"},"identityId":"YDbJw40NcoQp6Gx1lGdZOw","type":"ADD_ALIAS"},"ledgerTimestamp":1649986126707,"uuid":"vV8ed0N8aq51AMQS8gBcQg","version":"1"}
{"action":{"identity":{"address":"N\u0000sourcecred\u0000core\u0000IDENTITY\u0000ytM2guApjPwMR9B7h72Gdw\u0000","aliases":[],"id":"ytM2guApjPwMR9B7h72Gdw","name":"dnlmc","subtype":"USER"},"type":"CREATE_IDENTITY"},"ledgerTimestamp":1649986126707,"uuid":"q6DZq3JxD59v9tkYiWSYtg","version":"1"}
{"action":{"alias":{"address":"N\u0000sourcecred\u0000discord\u0000MEMBER\u0000user\u0000709960689682350150\u0000","description":"discord/dnlmc#6862"},"identityId":"ytM2guApjPwMR9B7h72Gdw","type":"ADD_ALIAS"},"ledgerTimestamp":1649986126708,"uuid":"8i1qLMydd6aUYwV8XnFErQ","version":"1"}
{"action":{"identity":{"address":"N\u0000sourcecred\u0000core\u0000IDENTITY\u0000Py5Gid5pWD6SZdYLdaqFlw\u0000","aliases":[],"id":"Py5Gid5pWD6SZdYLdaqFlw","name":"Jessica-Sacher","subtype":"USER"},"type":"CREATE_IDENTITY"},"ledgerTimestamp":1649986126708,"uuid":"quqkELX3XQBfX6DJC12OSw","version":"1"}
{"action":{"alias":{"address":"N\u0000sourcecred\u0000discord\u0000MEMBER\u0000user\u0000740984621482901546\u0000","description":"discord/Jessica-Sacher#8232"},"identityId":"Py5Gid5pWD6SZdYLdaqFlw","type":"ADD_ALIAS"},"ledgerTimestamp":1649986126708,"uuid":"8c4kYzZrA1r1VoaXE6N1fw","version":"1"}
{"action":{"identity":{"address":"N\u0000sourcecred\u0000core\u0000IDENTITY\u0000Eqdgdmsoza9InSGOyg25pg\u0000","aliases":[],"id":"Eqdgdmsoza9InSGOyg25pg","name":"JennyK","subtype":"USER"},"type":"CREATE_IDENTITY"},"ledgerTimestamp":1649986126708,"uuid":"cewn2RXsOl8ARBQv6g4f0g","version":"1"}
{"action":{"alias":{"address":"N\u0000sourcecred\u0000discord\u0000MEMBER\u0000user\u0000802642216170160128\u0000","description":"discord/JennyK#9454"},"identityId":"Eqdgdmsoza9InSGOyg25pg","type":"ADD_ALIAS"},"ledgerTimestamp":1649986126708,"uuid":"dlc2kv04pao9xdQ3knyNOg","version":"1"}
{"action":{"identity":{"address":"N\u0000sourcecred\u0000core\u0000IDENTITY\u00003O1eZfyaZrUYgMXRJBhMww\u0000","aliases":[],"id":"3O1eZfyaZrUYgMXRJBhMww","name":"daedelan","subtype":"USER"},"type":"CREATE_IDENTITY"},"ledgerTimestamp":1649986126708,"uuid":"RacYWuepADLi4jewmlhOmQ","version":"1"}
{"action":{"alias":{"address":"N\u0000sourcecred\u0000discord\u0000MEMBER\u0000user\u0000817949158732333056\u0000","description":"discord/daedelan#8161"},"identityId":"3O1eZfyaZrUYgMXRJBhMww","type":"ADD_ALIAS"},"ledgerTimestamp":1649986126709,"uuid":"EvL6xSYEoV2LeNmmDAfGOw","version":"1"}
{"action":{"identity":{"address":"N\u0000sourcecred\u0000core\u0000IDENTITY\u0000LMdYFdmZZMm6XaeEnpefWA\u0000","aliases":[],"id":"LMdYFdmZZMm6XaeEnpefWA","name":"ubuku--","subtype":"USER"},"type":"CREATE_IDENTITY"},"ledgerTimestamp":1649986126709,"uuid":"5klw4G7cR8aso4qfrtaFwQ","version":"1"}
{"action":{"alias":{"address":"N\u0000sourcecred\u0000discord\u0000MEMBER\u0000user\u0000828188261209473035\u0000","description":"discord/ubuku--#4148"},"identityId":"LMdYFdmZZMm6XaeEnpefWA","type":"ADD_ALIAS"},"ledgerTimestamp":1649986126709,"uuid":"NFb7r5x68ZvmivTPyYEyQw","version":"1"}
{"action":{"identity":{"address":"N\u0000sourcecred\u0000core\u0000IDENTITY\u0000wG9tLFVK4kKumPBsGKEmJA\u0000","aliases":[],"id":"wG9tLFVK4kKumPBsGKEmJA","name":"Varunkothamachu","subtype":"USER"},"type":"CREATE_IDENTITY"},"ledgerTimestamp":1649986126710,"uuid":"B1NW9VJz5q8NFmL8aeL9dw","version":"1"}
{"action":{"alias":{"address":"N\u0000sourcecred\u0000discord\u0000MEMBER\u0000user\u0000855086717744185345\u0000","description":"discord/Varunkothamachu#8751"},"identityId":"wG9tLFVK4kKumPBsGKEmJA","type":"ADD_ALIAS"},"ledgerTimestamp":1649986126710,"uuid":"jCVtYolqBXxoNMjBt6sNaQ","version":"1"}
{"action":{"identity":{"address":"N\u0000sourcecred\u0000core\u0000IDENTITY\u0000KXhQmHWTYe0VOdTJ33ideg\u0000","aliases":[],"id":"KXhQmHWTYe0VOdTJ33ideg","name":"geez","subtype":"USER"},"type":"CREATE_IDENTITY"},"ledgerTimestamp":1649986126710,"uuid":"8gv5fd2FGUJN56AouplEcg","version":"1"}
{"action":{"alias":{"address":"N\u0000sourcecred\u0000discord\u0000MEMBER\u0000user\u0000883286295533723670\u0000","description":"discord/geez#3883"},"identityId":"KXhQmHWTYe0VOdTJ33ideg","type":"ADD_ALIAS"},"ledgerTimestamp":1649986126710,"uuid":"CWT7bzpWoqH3V495o1QeVg","version":"1"}
{"action":{"identity":{"address":"N\u0000sourcecred\u0000core\u0000IDENTITY\u0000gkdoeQG4OW94KreSz0o2cg\u0000","aliases":[],"id":"gkdoeQG4OW94KreSz0o2cg","name":"skoth","subtype":"USER"},"type":"CREATE_IDENTITY"},"ledgerTimestamp":1649986126710,"uuid":"7u6ayLO74UVFyGnrvhjAbA","version":"1"}
{"action":{"alias":{"address":"N\u0000sourcecred\u0000discord\u0000MEMBER\u0000user\u0000910935955324686439\u0000","description":"discord/skoth#8973"},"identityId":"gkdoeQG4OW94KreSz0o2cg","type":"ADD_ALIAS"},"ledgerTimestamp":1649986126710,"uuid":"4gNl8V88u2bD9JAXwPUPxQ","version":"1"}
{"action":{"identity":{"address":"N\u0000sourcecred\u0000core\u0000IDENTITY\u0000451EZmgrCY7mgfmR8Pnl2A\u0000","aliases":[],"id":"451EZmgrCY7mgfmR8Pnl2A","name":"sciaddict","subtype":"USER"},"type":"CREATE_IDENTITY"},"ledgerTimestamp":1649986126710,"uuid":"pv3XxAYaL53LOzoVKNFVIg","version":"1"}
{"action":{"alias":{"address":"N\u0000sourcecred\u0000discord\u0000MEMBER\u0000user\u0000935375112499265566\u0000","description":"discord/sciaddict#8938"},"identityId":"451EZmgrCY7mgfmR8Pnl2A","type":"ADD_ALIAS"},"ledgerTimestamp":1649986126711,"uuid":"T15E3uDA94NxKOj9PeBE7w","version":"1"}
{"action":{"identity":{"address":"N\u0000sourcecred\u0000core\u0000IDENTITY\u0000nYCOoyaGxIpiBxYlyIr65w\u0000","aliases":[],"id":"nYCOoyaGxIpiBxYlyIr65w","name":"Psychonaut","subtype":"USER"},"type":"CREATE_IDENTITY"},"ledgerTimestamp":1649986126711,"uuid":"WbVFDOhwzSQs0CrqwnXEEQ","version":"1"}
{"action":{"alias":{"address":"N\u0000sourcecred\u0000discord\u0000MEMBER\u0000user\u0000111882829838684160\u0000","description":"discord/Psychonaut#0216"},"identityId":"nYCOoyaGxIpiBxYlyIr65w","type":"ADD_ALIAS"},"ledgerTimestamp":1649986126711,"uuid":"6IM0dY63bcXlxYdP9uVGzg","version":"1"}
{"action":{"identity":{"address":"N\u0000sourcecred\u0000core\u0000IDENTITY\u0000YwvLaDSqarXkm3l83uAu8A\u0000","aliases":[],"id":"YwvLaDSqarXkm3l83uAu8A","name":"Sina-Iman","subtype":"USER"},"type":"CREATE_IDENTITY"},"ledgerTimestamp":1649986126711,"uuid":"ij567wyKEW9TxloJSaNEtw","version":"1"}
{"action":{"alias":{"address":"N\u0000sourcecred\u0000discord\u0000MEMBER\u0000user\u0000192042086021726208\u0000","description":"discord/Sina-Iman#2897"},"identityId":"YwvLaDSqarXkm3l83uAu8A","type":"ADD_ALIAS"},"ledgerTimestamp":1649986126711,"uuid":"wxeSOi78998osN9n66vV7Q","version":"1"}
{"action":{"identity":{"address":"N\u0000sourcecred\u0000core\u0000IDENTITY\u0000low80NW70pFodKVBJ7FVYQ\u0000","aliases":[],"id":"low80NW70pFodKVBJ7FVYQ","name":"kabat","subtype":"USER"},"type":"CREATE_IDENTITY"},"ledgerTimestamp":1649986126711,"uuid":"g7mmDbHGCgkwtJkATNSaPQ","version":"1"}
{"action":{"alias":{"address":"N\u0000sourcecred\u0000discord\u0000MEMBER\u0000user\u0000204335630291959809\u0000","description":"discord/kabat#3484"},"identityId":"low80NW70pFodKVBJ7FVYQ","type":"ADD_ALIAS"},"ledgerTimestamp":1649986126711,"uuid":"DcPu9y0FQlPVT3Qt4vI72A","version":"1"}
{"action":{"identity":{"address":"N\u0000sourcecred\u0000core\u0000IDENTITY\u0000x0LxOjR8nNvZtQAzzdbAQw\u0000","aliases":[],"id":"x0LxOjR8nNvZtQAzzdbAQw","name":"Braid","subtype":"BOT"},"type":"CREATE_IDENTITY"},"ledgerTimestamp":1649986126711,"uuid":"8gmZLltRLrLyhWTaB6APog","version":"1"}
{"action":{"alias":{"address":"N\u0000sourcecred\u0000discord\u0000MEMBER\u0000bot\u0000235148962103951360\u0000","description":"discord/Braid#1536"},"identityId":"x0LxOjR8nNvZtQAzzdbAQw","type":"ADD_ALIAS"},"ledgerTimestamp":1649986126711,"uuid":"IrHnpmrNAHek6E9EaG3z1w","version":"1"}
{"action":{"identity":{"address":"N\u0000sourcecred\u0000core\u0000IDENTITY\u00008uRO27acMTkbvpzAMee8rA\u0000","aliases":[],"id":"8uRO27acMTkbvpzAMee8rA","name":"with-heart","subtype":"USER"},"type":"CREATE_IDENTITY"},"ledgerTimestamp":1649986126712,"uuid":"HB0LeLIyCne8naQZWrEAbA","version":"1"}
{"action":{"alias":{"address":"N\u0000sourcecred\u0000discord\u0000MEMBER\u0000user\u0000256500797959831552\u0000","description":"discord/with-heart#0001"},"identityId":"8uRO27acMTkbvpzAMee8rA","type":"ADD_ALIAS"},"ledgerTimestamp":1649986126712,"uuid":"FB4VPbS3O8YSe8ycQXuRzA","version":"1"}
{"action":{"identity":{"address":"N\u0000sourcecred\u0000core\u0000IDENTITY\u0000qtrh9KgEsJpWnIQNRreC7A\u0000","aliases":[],"id":"qtrh9KgEsJpWnIQNRreC7A","name":"Zira","subtype":"BOT"},"type":"CREATE_IDENTITY"},"ledgerTimestamp":1649986126712,"uuid":"gvZn2NKTzNFB3jjxHX2aOg","version":"1"}
{"action":{"alias":{"address":"N\u0000sourcecred\u0000discord\u0000MEMBER\u0000bot\u0000275813801792634880\u0000","description":"discord/Zira#9472"},"identityId":"qtrh9KgEsJpWnIQNRreC7A","type":"ADD_ALIAS"},"ledgerTimestamp":1649986126712,"uuid":"hbzVZZFPRBmlXy51wBlwNg","version":"1"}
{"action":{"identity":{"address":"N\u0000sourcecred\u0000core\u0000IDENTITY\u0000PX3orzM6sZmBX9XUrJzTaA\u0000","aliases":[],"id":"PX3orzM6sZmBX9XUrJzTaA","name":"iwa","subtype":"USER"},"type":"CREATE_IDENTITY"},"ledgerTimestamp":1649986126712,"uuid":"5QXWNkgYl5bzTVYQ8P1ydw","version":"1"}
{"action":{"alias":{"address":"N\u0000sourcecred\u0000discord\u0000MEMBER\u0000user\u0000310798814317379585\u0000","description":"discord/iwa#9749"},"identityId":"PX3orzM6sZmBX9XUrJzTaA","type":"ADD_ALIAS"},"ledgerTimestamp":1649986126712,"uuid":"m1r023TdBRuDwzIVqmat2A","version":"1"}
{"action":{"identity":{"address":"N\u0000sourcecred\u0000core\u0000IDENTITY\u00008kW9Zxe7UJbAEKJXcglcVw\u0000","aliases":[],"id":"8kW9Zxe7UJbAEKJXcglcVw","name":"anush","subtype":"USER"},"type":"CREATE_IDENTITY"},"ledgerTimestamp":1649986126713,"uuid":"z1f1wEL4FAygkgweZn3Vlg","version":"1"}
{"action":{"alias":{"address":"N\u0000sourcecred\u0000discord\u0000MEMBER\u0000user\u0000362218200890474497\u0000","description":"discord/anush#7771"},"identityId":"8kW9Zxe7UJbAEKJXcglcVw","type":"ADD_ALIAS"},"ledgerTimestamp":1649986126713,"uuid":"Wfw71hQMk2AILHexw9avwA","version":"1"}
{"action":{"identity":{"address":"N\u0000sourcecred\u0000core\u0000IDENTITY\u00000l3bm8gGZwHAZNVYxbRQlw\u0000","aliases":[],"id":"0l3bm8gGZwHAZNVYxbRQlw","name":"willsputra---Gitcoin","subtype":"USER"},"type":"CREATE_IDENTITY"},"ledgerTimestamp":1649986126713,"uuid":"I807yKJsVJBVED410sDneA","version":"1"}
{"action":{"alias":{"address":"N\u0000sourcecred\u0000discord\u0000MEMBER\u0000user\u0000375850432750157828\u0000","description":"discord/willsputra---Gitcoin#7177"},"identityId":"0l3bm8gGZwHAZNVYxbRQlw","type":"ADD_ALIAS"},"ledgerTimestamp":1649986126713,"uuid":"eKn0z1PSzHbhM7jrwcbMdg","version":"1"}
{"action":{"identity":{"address":"N\u0000sourcecred\u0000core\u0000IDENTITY\u0000pV7t3WcL2yON0BomfoyfoQ\u0000","aliases":[],"id":"pV7t3WcL2yON0BomfoyfoQ","name":"tobystic","subtype":"USER"},"type":"CREATE_IDENTITY"},"ledgerTimestamp":1649986126713,"uuid":"d6Irzz60i3z7adkMOfx02Q","version":"1"}
{"action":{"alias":{"address":"N\u0000sourcecred\u0000discord\u0000MEMBER\u0000user\u0000514565183964839939\u0000","description":"discord/tobystic#5007"},"identityId":"pV7t3WcL2yON0BomfoyfoQ","type":"ADD_ALIAS"},"ledgerTimestamp":1649986126713,"uuid":"8unr2cw7vLTYizGsPzJ6CA","version":"1"}
{"action":{"identity":{"address":"N\u0000sourcecred\u0000core\u0000IDENTITY\u0000PlQAARe3D8T9cNemqaew6g\u0000","aliases":[],"id":"PlQAARe3D8T9cNemqaew6g","name":"Chopras---42OPE","subtype":"USER"},"type":"CREATE_IDENTITY"},"ledgerTimestamp":1649986126713,"uuid":"ioGm3IEmBYApnwfNpvVM9w","version":"1"}
{"action":{"alias":{"address":"N\u0000sourcecred\u0000discord\u0000MEMBER\u0000user\u0000537474612620034069\u0000","description":"discord/Chopras---42OPE#4998"},"identityId":"PlQAARe3D8T9cNemqaew6g","type":"ADD_ALIAS"},"ledgerTimestamp":1649986126713,"uuid":"58MgW6uJ2xUo3idb7jjhbQ","version":"1"}
{"action":{"identity":{"address":"N\u0000sourcecred\u0000core\u0000IDENTITY\u0000crxUJneobj9qiZhKc2QznA\u0000","aliases":[],"id":"crxUJneobj9qiZhKc2QznA","name":"saulthorin","subtype":"USER"},"type":"CREATE_IDENTITY"},"ledgerTimestamp":1649986126714,"uuid":"j2R7Uqd4mtbyRILURenTlA","version":"1"}
{"action":{"alias":{"address":"N\u0000sourcecred\u0000discord\u0000MEMBER\u0000user\u0000579128660070760469\u0000","description":"discord/saulthorin#7696"},"identityId":"crxUJneobj9qiZhKc2QznA","type":"ADD_ALIAS"},"ledgerTimestamp":1649986126714,"uuid":"xMLrgRZybgSniZDBMZjxsA","version":"1"}
{"action":{"identity":{"address":"N\u0000sourcecred\u0000core\u0000IDENTITY\u0000wyCM6O68l81ZQJrdpYqGIQ\u0000","aliases":[],"id":"wyCM6O68l81ZQJrdpYqGIQ","name":"kara","subtype":"USER"},"type":"CREATE_IDENTITY"},"ledgerTimestamp":1649986126714,"uuid":"d0r0ODGS7whZAS5yAFVq2Q","version":"1"}
{"action":{"alias":{"address":"N\u0000sourcecred\u0000discord\u0000MEMBER\u0000user\u0000630866784970604564\u0000","description":"discord/kara#0038"},"identityId":"wyCM6O68l81ZQJrdpYqGIQ","type":"ADD_ALIAS"},"ledgerTimestamp":1649986126714,"uuid":"ykUmdMforyUmt8Mpwy61qw","version":"1"}
{"action":{"identity":{"address":"N\u0000sourcecred\u0000core\u0000IDENTITY\u00005u2mtvA0k3ZxfejUWRxeSA\u0000","aliases":[],"id":"5u2mtvA0k3ZxfejUWRxeSA","name":"Urek","subtype":"USER"},"type":"CREATE_IDENTITY"},"ledgerTimestamp":1649986126714,"uuid":"UjModyRLjbqhdcbYyzXF7Q","version":"1"}
{"action":{"alias":{"address":"N\u0000sourcecred\u0000discord\u0000MEMBER\u0000user\u0000653878275902275615\u0000","description":"discord/Urek#5014"},"identityId":"5u2mtvA0k3ZxfejUWRxeSA","type":"ADD_ALIAS"},"ledgerTimestamp":1649986126714,"uuid":"ZH7zU0rmg17unLEL3WqfVA","version":"1"}
{"action":{"identity":{"address":"N\u0000sourcecred\u0000core\u0000IDENTITY\u00000G2xV4Ahm9xJnWS3GVy0Fg\u0000","aliases":[],"id":"0G2xV4Ahm9xJnWS3GVy0Fg","name":"Parikshit","subtype":"USER"},"type":"CREATE_IDENTITY"},"ledgerTimestamp":1649986126714,"uuid":"N0foDyjOf7dQTqrF5U1aVA","version":"1"}
{"action":{"alias":{"address":"N\u0000sourcecred\u0000discord\u0000MEMBER\u0000user\u0000688156591157280768\u0000","description":"discord/Parikshit#5181"},"identityId":"0G2xV4Ahm9xJnWS3GVy0Fg","type":"ADD_ALIAS"},"ledgerTimestamp":1649986126714,"uuid":"spAE9YBP2hoi28IlGDVOWg","version":"1"}
{"action":{"identity":{"address":"N\u0000sourcecred\u0000core\u0000IDENTITY\u0000yX1ySx0nIVLrypWru4gnLg\u0000","aliases":[],"id":"yX1ySx0nIVLrypWru4gnLg","name":"jayy-leww","subtype":"USER"},"type":"CREATE_IDENTITY"},"ledgerTimestamp":1649986126715,"uuid":"rs4WpvqJpjGvMETYpdbB9Q","version":"1"}
{"action":{"alias":{"address":"N\u0000sourcecred\u0000discord\u0000MEMBER\u0000user\u0000689941282016985122\u0000","description":"discord/jayy-leww#6202"},"identityId":"yX1ySx0nIVLrypWru4gnLg","type":"ADD_ALIAS"},"ledgerTimestamp":1649986126715,"uuid":"3FYB58unawzWd1A1zrLWHg","version":"1"}
{"action":{"identity":{"address":"N\u0000sourcecred\u0000core\u0000IDENTITY\u0000lUNH7hdBBLawoypeAVXggw\u0000","aliases":[],"id":"lUNH7hdBBLawoypeAVXggw","name":"KP","subtype":"USER"},"type":"CREATE_IDENTITY"},"ledgerTimestamp":1649986126715,"uuid":"v4JxJGtm0WdIqeWwRkzo5A","version":"1"}
{"action":{"alias":{"address":"N\u0000sourcecred\u0000discord\u0000MEMBER\u0000user\u0000692753047910350859\u0000","description":"discord/KP#5339"},"identityId":"lUNH7hdBBLawoypeAVXggw","type":"ADD_ALIAS"},"ledgerTimestamp":1649986126715,"uuid":"HBRFv7Z9c9OJG6uQCnkeAg","version":"1"}
{"action":{"identity":{"address":"N\u0000sourcecred\u0000core\u0000IDENTITY\u00009gUxPOOYzNm6GcevJncP3A\u0000","aliases":[],"id":"9gUxPOOYzNm6GcevJncP3A","name":"oatmeal4m3","subtype":"USER"},"type":"CREATE_IDENTITY"},"ledgerTimestamp":1649986126716,"uuid":"QaJXLoD0qEafaNvdhVv1gw","version":"1"}
{"action":{"alias":{"address":"N\u0000sourcecred\u0000discord\u0000MEMBER\u0000user\u0000694062161831395358\u0000","description":"discord/oatmeal4m3#8042"},"identityId":"9gUxPOOYzNm6GcevJncP3A","type":"ADD_ALIAS"},"ledgerTimestamp":1649986126716,"uuid":"d10E6Gd0jAuZ0oHgu3OG1A","version":"1"}
{"action":{"identity":{"address":"N\u0000sourcecred\u0000core\u0000IDENTITY\u0000PjO7yaJIeUxoXtm5FNhD4w\u0000","aliases":[],"id":"PjO7yaJIeUxoXtm5FNhD4w","name":"Jakub","subtype":"USER"},"type":"CREATE_IDENTITY"},"ledgerTimestamp":1649986126716,"uuid":"dHPry0WReTg6r2L1GeBjvg","version":"1"}
{"action":{"alias":{"address":"N\u0000sourcecred\u0000discord\u0000MEMBER\u0000user\u0000698615884889194587\u0000","description":"discord/Jakub#3317"},"identityId":"PjO7yaJIeUxoXtm5FNhD4w","type":"ADD_ALIAS"},"ledgerTimestamp":1649986126716,"uuid":"NfZYoDvyWI6SwIqkzlfR2w","version":"1"}
{"action":{"identity":{"address":"N\u0000sourcecred\u0000core\u0000IDENTITY\u0000cNQrIlJQmTw4fPCNjNIyIw\u0000","aliases":[],"id":"cNQrIlJQmTw4fPCNjNIyIw","name":"Nimi-Vashi","subtype":"USER"},"type":"CREATE_IDENTITY"},"ledgerTimestamp":1649986126716,"uuid":"bzh7XynF6GXXBCMlhwl1fw","version":"1"}
{"action":{"alias":{"address":"N\u0000sourcecred\u0000discord\u0000MEMBER\u0000user\u0000699013714317148210\u0000","description":"discord/Nimi-Vashi#8251"},"identityId":"cNQrIlJQmTw4fPCNjNIyIw","type":"ADD_ALIAS"},"ledgerTimestamp":1649986126716,"uuid":"4q1zVf7pmVEjR2y3Wz2gIA","version":"1"}
{"action":{"identity":{"address":"N\u0000sourcecred\u0000core\u0000IDENTITY\u000036bP6OX9uLDrPZjkfEgLwg\u0000","aliases":[],"id":"36bP6OX9uLDrPZjkfEgLwg","name":"solaria","subtype":"USER"},"type":"CREATE_IDENTITY"},"ledgerTimestamp":1649986126716,"uuid":"cQOK6PjmjkQSpCnH0rU6Xw","version":"1"}
{"action":{"alias":{"address":"N\u0000sourcecred\u0000discord\u0000MEMBER\u0000user\u0000699442991110029362\u0000","description":"discord/solaria#0001"},"identityId":"36bP6OX9uLDrPZjkfEgLwg","type":"ADD_ALIAS"},"ledgerTimestamp":1649986126716,"uuid":"t14Ul6RRgL82Qphz3KTrAQ","version":"1"}
{"action":{"identity":{"address":"N\u0000sourcecred\u0000core\u0000IDENTITY\u00005eQYdRGP0v7UDQ8ACzyT8g\u0000","aliases":[],"id":"5eQYdRGP0v7UDQ8ACzyT8g","name":"ActiveInferenceLab","subtype":"USER"},"type":"CREATE_IDENTITY"},"ledgerTimestamp":1649986126717,"uuid":"9WOCjWBLR6tR3aY9xflddg","version":"1"}
{"action":{"alias":{"address":"N\u0000sourcecred\u0000discord\u0000MEMBER\u0000user\u0000722593944466096134\u0000","description":"discord/ActiveInferenceLab#3629"},"identityId":"5eQYdRGP0v7UDQ8ACzyT8g","type":"ADD_ALIAS"},"ledgerTimestamp":1649986126717,"uuid":"JyvyA7nsJVy3Pcw7tWAx1w","version":"1"}
{"action":{"identity":{"address":"N\u0000sourcecred\u0000core\u0000IDENTITY\u0000RwXa0O4WCKvWvsmjcVv46g\u0000","aliases":[],"id":"RwXa0O4WCKvWvsmjcVv46g","name":"vincenzospaghetti","subtype":"USER"},"type":"CREATE_IDENTITY"},"ledgerTimestamp":1649986126717,"uuid":"cydfprckCYAZecz5P4peZQ","version":"1"}
{"action":{"alias":{"address":"N\u0000sourcecred\u0000discord\u0000MEMBER\u0000user\u0000771410459798274109\u0000","description":"discord/vincenzospaghetti#8265"},"identityId":"RwXa0O4WCKvWvsmjcVv46g","type":"ADD_ALIAS"},"ledgerTimestamp":1649986126717,"uuid":"8yZgQkqqUraDBJ4Mm0jJhw","version":"1"}
{"action":{"identity":{"address":"N\u0000sourcecred\u0000core\u0000IDENTITY\u0000P9nrilgbYnTLwj1HEceHkg\u0000","aliases":[],"id":"P9nrilgbYnTLwj1HEceHkg","name":"vintro","subtype":"USER"},"type":"CREATE_IDENTITY"},"ledgerTimestamp":1649986126717,"uuid":"Nu66qmMypu3qrv0LFyWT4Q","version":"1"}
{"action":{"alias":{"address":"N\u0000sourcecred\u0000discord\u0000MEMBER\u0000user\u0000782729216461897798\u0000","description":"discord/vintro#1873"},"identityId":"P9nrilgbYnTLwj1HEceHkg","type":"ADD_ALIAS"},"ledgerTimestamp":1649986126717,"uuid":"wbbyzLgp2vol9w8uVFoX8g","version":"1"}
{"action":{"identity":{"address":"N\u0000sourcecred\u0000core\u0000IDENTITY\u0000NjiVgsABasaLcRpsDlHqcQ\u0000","aliases":[],"id":"NjiVgsABasaLcRpsDlHqcQ","name":"nicklinck","subtype":"USER"},"type":"CREATE_IDENTITY"},"ledgerTimestamp":1649986126718,"uuid":"RH6mGMPeSoXyyJGasREf3w","version":"1"}
{"action":{"alias":{"address":"N\u0000sourcecred\u0000discord\u0000MEMBER\u0000user\u0000783927840638369812\u0000","description":"discord/nicklinck#6691"},"identityId":"NjiVgsABasaLcRpsDlHqcQ","type":"ADD_ALIAS"},"ledgerTimestamp":1649986126718,"uuid":"X0EmRdp3SROEoSqXUDLQLw","version":"1"}
{"action":{"identity":{"address":"N\u0000sourcecred\u0000core\u0000IDENTITY\u0000FbTJUpLWV8szJt3HY4rsxw\u0000","aliases":[],"id":"FbTJUpLWV8szJt3HY4rsxw","name":"BruceLee","subtype":"USER"},"type":"CREATE_IDENTITY"},"ledgerTimestamp":1649986126718,"uuid":"5yxPPXSnj8AU6BlkYGYg5w","version":"1"}
{"action":{"alias":{"address":"N\u0000sourcecred\u0000discord\u0000MEMBER\u0000user\u0000805181666959425566\u0000","description":"discord/BruceLee#8378"},"identityId":"FbTJUpLWV8szJt3HY4rsxw","type":"ADD_ALIAS"},"ledgerTimestamp":1649986126718,"uuid":"T3HAsojPHyJQeT7xh3qDTA","version":"1"}
{"action":{"identity":{"address":"N\u0000sourcecred\u0000core\u0000IDENTITY\u00009t6oPjAmVETMksgJmogAtA\u0000","aliases":[],"id":"9t6oPjAmVETMksgJmogAtA","name":"nnsk","subtype":"USER"},"type":"CREATE_IDENTITY"},"ledgerTimestamp":1649986126718,"uuid":"LjBd1QQ1h8bdfrUlHZqxFg","version":"1"}
{"action":{"alias":{"address":"N\u0000sourcecred\u0000discord\u0000MEMBER\u0000user\u0000819725310919442472\u0000","description":"discord/nnsk#4182"},"identityId":"9t6oPjAmVETMksgJmogAtA","type":"ADD_ALIAS"},"ledgerTimestamp":1649986126718,"uuid":"jRztefzsxokoI62Nr3q6Kw","version":"1"}
{"action":{"identity":{"address":"N\u0000sourcecred\u0000core\u0000IDENTITY\u0000zpDoP5DF4Mnpgi0S19mgdQ\u0000","aliases":[],"id":"zpDoP5DF4Mnpgi0S19mgdQ","name":"DAOlan","subtype":"USER"},"type":"CREATE_IDENTITY"},"ledgerTimestamp":1649986126719,"uuid":"aHAEE3z3neB0graSklz4TQ","version":"1"}
{"action":{"alias":{"address":"N\u0000sourcecred\u0000discord\u0000MEMBER\u0000user\u0000820450750160830465\u0000","description":"discord/DAOlan#3666"},"identityId":"zpDoP5DF4Mnpgi0S19mgdQ","type":"ADD_ALIAS"},"ledgerTimestamp":1649986126720,"uuid":"K3CKOFe3yGOhx1c2iMAqSw","version":"1"}
{"action":{"identity":{"address":"N\u0000sourcecred\u0000core\u0000IDENTITY\u0000igO1JnzyO5zi4iMUB4w7Rw\u0000","aliases":[],"id":"igO1JnzyO5zi4iMUB4w7Rw","name":"Dario-Nelson","subtype":"USER"},"type":"CREATE_IDENTITY"},"ledgerTimestamp":1649986126720,"uuid":"xSns1Yat39BBCJPIB9Yyng","version":"1"}
{"action":{"alias":{"address":"N\u0000sourcecred\u0000discord\u0000MEMBER\u0000user\u0000825462846410326098\u0000","description":"discord/Dario-Nelson#4220"},"identityId":"igO1JnzyO5zi4iMUB4w7Rw","type":"ADD_ALIAS"},"ledgerTimestamp":1649986126720,"uuid":"tMlDKFv1BtDoQCbe4DY0mQ","version":"1"}
{"action":{"identity":{"address":"N\u0000sourcecred\u0000core\u0000IDENTITY\u0000yFRfXfORf5OzOOTbNnx9rA\u0000","aliases":[],"id":"yFRfXfORf5OzOOTbNnx9rA","name":"Radiant-Ad-9137","subtype":"USER"},"type":"CREATE_IDENTITY"},"ledgerTimestamp":1649986126720,"uuid":"JKVJWTDcB2hN6ForrWO3BQ","version":"1"}
{"action":{"alias":{"address":"N\u0000sourcecred\u0000discord\u0000MEMBER\u0000user\u0000825766730361208923\u0000","description":"discord/Radiant-Ad-9137#6939"},"identityId":"yFRfXfORf5OzOOTbNnx9rA","type":"ADD_ALIAS"},"ledgerTimestamp":1649986126720,"uuid":"zae1eXH15jDMn1SkgQzlqQ","version":"1"}
{"action":{"identity":{"address":"N\u0000sourcecred\u0000core\u0000IDENTITY\u0000oqWTKxvToW9WL2TQdKyC4g\u0000","aliases":[],"id":"oqWTKxvToW9WL2TQdKyC4g","name":"an-libertine","subtype":"USER"},"type":"CREATE_IDENTITY"},"ledgerTimestamp":1649986126721,"uuid":"GwVEj3tN0IaCBD3Ok1xp2w","version":"1"}
{"action":{"alias":{"address":"N\u0000sourcecred\u0000discord\u0000MEMBER\u0000user\u0000859519093152415754\u0000","description":"discord/an-libertine#3342"},"identityId":"oqWTKxvToW9WL2TQdKyC4g","type":"ADD_ALIAS"},"ledgerTimestamp":1649986126721,"uuid":"B8Pq1ePeqm5IaGE0Aek1LQ","version":"1"}
{"action":{"identity":{"address":"N\u0000sourcecred\u0000core\u0000IDENTITY\u0000toeHVi5XUaK7aK14oAlWFA\u0000","aliases":[],"id":"toeHVi5XUaK7aK14oAlWFA","name":"sidcode","subtype":"USER"},"type":"CREATE_IDENTITY"},"ledgerTimestamp":1649986126721,"uuid":"SQOqZoGz7Jje25tzFbMfnA","version":"1"}
{"action":{"alias":{"address":"N\u0000sourcecred\u0000discord\u0000MEMBER\u0000user\u0000861513367700111360\u0000","description":"discord/sidcode#1729"},"identityId":"toeHVi5XUaK7aK14oAlWFA","type":"ADD_ALIAS"},"ledgerTimestamp":1649986126721,"uuid":"edkq3787cbWCAWXMY4AnaA","version":"1"}
{"action":{"identity":{"address":"N\u0000sourcecred\u0000core\u0000IDENTITY\u0000KcDJGa8ryxEmI4x7OlLPNA\u0000","aliases":[],"id":"KcDJGa8ryxEmI4x7OlLPNA","name":"carlaost","subtype":"USER"},"type":"CREATE_IDENTITY"},"ledgerTimestamp":1649986126721,"uuid":"oKZA1wdWmjMBqoZJPqOvdw","version":"1"}
{"action":{"alias":{"address":"N\u0000sourcecred\u0000discord\u0000MEMBER\u0000user\u0000910940211754700882\u0000","description":"discord/carlaost#5298"},"identityId":"KcDJGa8ryxEmI4x7OlLPNA","type":"ADD_ALIAS"},"ledgerTimestamp":1649986126721,"uuid":"crBUqZoIGBTGEWp0oNMenw","version":"1"}
{"action":{"identity":{"address":"N\u0000sourcecred\u0000core\u0000IDENTITY\u0000Uaso6OSA4w6dr12Gjyzerg\u0000","aliases":[],"id":"Uaso6OSA4w6dr12Gjyzerg","name":"laura314","subtype":"USER"},"type":"CREATE_IDENTITY"},"ledgerTimestamp":1649986126722,"uuid":"FKcw84VyIdjw3At8fyYIvA","version":"1"}
{"action":{"alias":{"address":"N\u0000sourcecred\u0000discord\u0000MEMBER\u0000user\u0000921239888039391313\u0000","description":"discord/laura314#2123"},"identityId":"Uaso6OSA4w6dr12Gjyzerg","type":"ADD_ALIAS"},"ledgerTimestamp":1649986126722,"uuid":"UpjDZPDZkgHb3vBKKv9xPw","version":"1"}
